[{"tag":"財經","count":22,"articles":[{"topic":"反送中催化　香港人來台居留人數破萬","dates":"02/24 23:55","url":"https://www.setn.com/News.aspx?NewsID=901828&utm_source=setn.com&utm_medium=viewall&utm_campaign=viewallnews"},{"topic":"疫情持續影響　陸商務部：穩住基本盤","dates":"02/24 23:22","url":"https://www.setn.com/News.aspx?NewsID=901713&utm_source=setn.com&utm_medium=viewall&utm_campaign=viewallnews"},{"topic":"首度！國際信評機構調升台灣評等","dates":"02/24 23:11","url":"https://www.setn.com/News.aspx?NewsID=901817&utm_source=setn.com&utm_medium=viewall&utm_campaign=viewallnews"},{"topic":"僅開放一台電腦　商家排隊發票氣噗噗","dates":"02/24 22:29","url":"https://www.setn.com/News.aspx?NewsID=901768&utm_source=setn.com&utm_medium=viewall&utm_campaign=viewallnews"},{"topic":"蘇貞昌拍板　節能電器獎勵延長2年","dates":"02/24 22:10","url":"https://www.setn.com/News.aspx?NewsID=901813&utm_source=setn.com&utm_medium=viewall&utm_campaign=viewallnews"},{"topic":"牛年理財術／專家：股票比例可佔5成","dates":"02/24 21:48","url":"https://www.setn.com/News.aspx?NewsID=901827&utm_source=setn.com&utm_medium=viewall&utm_campaign=viewallnews"},{"topic":"鴻海攜手Fisker　2年後推新車","dates":"02/24 21:04","url":"https://www.setn.com/News.aspx?NewsID=901816&utm_source=setn.com&utm_medium=viewall&utm_campaign=viewallnews"},{"topic":"金金併首例　公平會著眼2大關鍵通過","dates":"02/24 19:42","url":"https://www.setn.com/News.aspx?NewsID=901793&utm_source=setn.com&utm_medium=viewall&utm_campaign=viewallnews"},{"topic":"竹科節水率提高　台積電緊急出動水車","dates":"02/24 18:15","url":"https://www.setn.com/News.aspx?NewsID=901618&utm_source=setn.com&utm_medium=viewall&utm_campaign=viewallnews"},{"topic":"富邦金併日盛金　公平會點頭通過","dates":"02/24 17:48","url":"https://www.setn.com/News.aspx?NewsID=901719&utm_source=setn.com&utm_medium=viewall&utm_campaign=viewallnews"},{"topic":"新台幣貶0.4分　收28.306元","dates":"02/24 17:10","url":"https://www.setn.com/News.aspx?NewsID=901681&utm_source=setn.com&utm_medium=viewall&utm_campaign=viewallnews"},{"topic":"牛年開市最低！台股終場下挫230點","dates":"02/24 16:08","url":"https://www.setn.com/News.aspx?NewsID=901640&utm_source=setn.com&utm_medium=viewall&utm_campaign=viewallnews"},{"topic":"台積電連5殺！台股收盤重挫230點","dates":"02/24 13:43","url":"https://www.setn.com/News.aspx?NewsID=901517&utm_source=setn.com&utm_medium=viewall&utm_campaign=viewallnews"},{"topic":"金融傳產撐盤　台股開低震盪整理","dates":"02/24 12:48","url":"https://www.setn.com/News.aspx?NewsID=901497&utm_source=setn.com&utm_medium=viewall&utm_campaign=viewallnews"},{"topic":"市值慘跌！台積電股價創牛年來新低","dates":"02/24 11:25","url":"https://www.setn.com/News.aspx?NewsID=901457&utm_source=setn.com&utm_medium=viewall&utm_campaign=viewallnews"},{"topic":"台股開盤跌113.86點　新台幣升","dates":"02/24 09:23","url":"https://www.setn.com/News.aspx?NewsID=901382&utm_source=setn.com&utm_medium=viewall&utm_campaign=viewallnews"},{"topic":"新／台積電跌2%　台股跌百點防震盪","dates":"02/24 09:01","url":"https://www.setn.com/News.aspx?NewsID=901361&utm_source=setn.com&utm_medium=viewall&utm_campaign=viewallnews"},{"topic":"劉揚偉操盤電動車　老裕隆人3字形容","dates":"02/24 08:43","url":"https://www.setn.com/News.aspx?NewsID=901360&utm_source=setn.com&utm_medium=viewall&utm_campaign=viewallnews"},{"topic":"獨／台積電熄火！他曝7大「元宵股」","dates":"02/24 08:30","url":"https://www.setn.com/News.aspx?NewsID=901164&utm_source=setn.com&utm_medium=viewall&utm_campaign=viewallnews"},{"topic":"道瓊、標普由黑翻紅　科技股那指收低","dates":"02/24 07:27","url":"https://www.setn.com/News.aspx?NewsID=901331&utm_source=setn.com&utm_medium=viewall&utm_campaign=viewallnews"},{"topic":"鴻海「打群架」　3款電動車年底上路","dates":"02/24 07:26","url":"https://www.setn.com/News.aspx?NewsID=901338&utm_source=setn.com&utm_medium=viewall&utm_campaign=viewallnews"},{"topic":"大巨蛋試營運時程曝　辜仲諒組團插旗","dates":"02/24 06:59","url":"https://www.setn.com/News.aspx?NewsID=901327&utm_source=setn.com&utm_medium=viewall&utm_campaign=viewallnews"}]},{"tag":"國際","count":50,"articles":[{"topic":"美國務卿：尋求重返聯合國人權理事會","dates":"02/24 23:55","url":"https://www.setn.com/News.aspx?NewsID=901844&utm_source=setn.com&utm_medium=viewall&utm_campaign=viewallnews"},{"topic":"澳國會可望通過新聞媒體議價法修正案","dates":"02/24 23:49","url":"https://www.setn.com/News.aspx?NewsID=901714&utm_source=setn.com&utm_medium=viewall&utm_campaign=viewallnews"},{"topic":"韓國生育率全球最低　首爾僅0.64","dates":"02/24 23:44","url":"https://www.setn.com/News.aspx?NewsID=901788&utm_source=setn.com&utm_medium=viewall&utm_campaign=viewallnews"},{"topic":"創新低！日本去年僅87萬新生兒","dates":"02/24 23:33","url":"https://www.setn.com/News.aspx?NewsID=901717&utm_source=setn.com&utm_medium=viewall&utm_campaign=viewallnews"},{"topic":"妹被怪力拖進床底！爸驚恐發文結局毛","dates":"02/24 23:14","url":"https://www.setn.com/News.aspx?NewsID=901845&utm_source=setn.com&utm_medium=viewall&utm_campaign=viewallnews"},{"topic":"請家教孩成績飆升　家長一調畫面崩潰","dates":"02/24 22:59","url":"https://www.setn.com/News.aspx?NewsID=901849&utm_source=setn.com&utm_medium=viewall&utm_campaign=viewallnews"},{"topic":"起重機零件擊穿飛機　賠償金額超驚人","dates":"02/24 22:13","url":"https://www.setn.com/News.aspx?NewsID=901797&utm_source=setn.com&utm_medium=viewall&utm_campaign=viewallnews"},{"topic":"鬧鬼區送餐　他搭上經文電梯突飄香味","dates":"02/24 22:11","url":"https://www.setn.com/News.aspx?NewsID=901842&utm_source=setn.com&utm_medium=viewall&utm_campaign=viewallnews"},{"topic":"女童梳頭勾出整排蟲！網嚇：都還在跳","dates":"02/24 22:03","url":"https://www.setn.com/News.aspx?NewsID=901837&utm_source=setn.com&utm_medium=viewall&utm_campaign=viewallnews"},{"topic":"男交往送BMW分手提告討回　女氣炸","dates":"02/24 21:42","url":"https://www.setn.com/News.aspx?NewsID=901833&utm_source=setn.com&utm_medium=viewall&utm_campaign=viewallnews"},{"topic":"他花20億換6次心臟續命　醫：荒謬","dates":"02/24 21:31","url":"https://www.setn.com/News.aspx?NewsID=901809&utm_source=setn.com&utm_medium=viewall&utm_campaign=viewallnews"},{"topic":"錯失70億　她買樂透「差1碼」哭了","dates":"02/24 21:01","url":"https://www.setn.com/News.aspx?NewsID=901638&utm_source=setn.com&utm_medium=viewall&utm_campaign=viewallnews"},{"topic":"紅綠燈出現奇怪突起！網嚇：小心沒命","dates":"02/24 21:00","url":"https://www.setn.com/News.aspx?NewsID=901811&utm_source=setn.com&utm_medium=viewall&utm_campaign=viewallnews"},{"topic":"雪地見「藍色流浪狗」一追真相太殘忍","dates":"02/24 20:54","url":"https://www.setn.com/News.aspx?NewsID=901814&utm_source=setn.com&utm_medium=viewall&utm_campaign=viewallnews"},{"topic":"27歲男「求政府分配老婆」　遭嗆爆","dates":"02/24 20:35","url":"https://www.setn.com/News.aspx?NewsID=901803&utm_source=setn.com&utm_medium=viewall&utm_campaign=viewallnews"},{"topic":"台增4境外　日本擬解除緊急事態宣言","dates":"02/24 19:45","url":"https://www.setn.com/News.aspx?NewsID=901765&utm_source=setn.com&utm_medium=viewall&utm_campaign=viewallnews"},{"topic":"清純妹改良旗袍炸美胸　一秒成限制級","dates":"02/24 19:33","url":"https://www.setn.com/News.aspx?NewsID=901786&utm_source=setn.com&utm_medium=viewall&utm_campaign=viewallnews"},{"topic":"央視封殺NBA　傳3月恢復直播","dates":"02/24 19:09","url":"https://www.setn.com/News.aspx?NewsID=901715&utm_source=setn.com&utm_medium=viewall&utm_campaign=viewallnews"},{"topic":"13歲少年遭1刀刀「凌遲」再焚屍","dates":"02/24 19:08","url":"https://www.setn.com/News.aspx?NewsID=901776&utm_source=setn.com&utm_medium=viewall&utm_campaign=viewallnews"},{"topic":"傳給室友1句話　她一到機場瞬間爆哭","dates":"02/24 19:01","url":"https://www.setn.com/News.aspx?NewsID=901724&utm_source=setn.com&utm_medium=viewall&utm_campaign=viewallnews"},{"topic":"因尿布髒…夫妻用沸水淋2歲兒折磨死","dates":"02/24 18:22","url":"https://www.setn.com/News.aspx?NewsID=901737&utm_source=setn.com&utm_medium=viewall&utm_campaign=viewallnews"},{"topic":"日建築師操刀　村上春樹圖書館將開館","dates":"02/24 17:59","url":"https://www.setn.com/News.aspx?NewsID=901683&utm_source=setn.com&utm_medium=viewall&utm_campaign=viewallnews"},{"topic":"美國會擬推法案　抵抗中共對企業脅迫","dates":"02/24 17:17","url":"https://www.setn.com/News.aspx?NewsID=901684&utm_source=setn.com&utm_medium=viewall&utm_campaign=viewallnews"},{"topic":"陸學者研發　中國批准武肺新疫苗上市","dates":"02/24 17:09","url":"https://www.setn.com/News.aspx?NewsID=901625&utm_source=setn.com&utm_medium=viewall&utm_campaign=viewallnews"},{"topic":"20萬中國疫苗抵泰　總理赴機場親迎","dates":"02/24 17:05","url":"https://www.setn.com/News.aspx?NewsID=901626&utm_source=setn.com&utm_medium=viewall&utm_campaign=viewallnews"},{"topic":"希拉蕊跨足文壇　攜手暢銷作家寫小說","dates":"02/24 16:58","url":"https://www.setn.com/News.aspx?NewsID=901629&utm_source=setn.com&utm_medium=viewall&utm_campaign=viewallnews"},{"topic":"緬甸示威擴大　印尼宣布外長取消訪問","dates":"02/24 16:57","url":"https://www.setn.com/News.aspx?NewsID=901627&utm_source=setn.com&utm_medium=viewall&utm_campaign=viewallnews"},{"topic":"中國灑千萬劑疫苗　國台辦：惠及台灣","dates":"02/24 16:00","url":"https://www.setn.com/News.aspx?NewsID=901631&utm_source=setn.com&utm_medium=viewall&utm_campaign=viewallnews"},{"topic":"山壁崩塌百具棺材遭吞沒　屍骨到處漂","dates":"02/24 15:57","url":"https://www.setn.com/News.aspx?NewsID=901523&utm_source=setn.com&utm_medium=viewall&utm_campaign=viewallnews"},{"topic":"5歲女童墜13樓　愛犬成肉墊當場亡","dates":"02/24 15:56","url":"https://www.setn.com/News.aspx?NewsID=901622&utm_source=setn.com&utm_medium=viewall&utm_campaign=viewallnews"},{"topic":"今增4確診！全球10大疫區一次看","dates":"02/24 15:21","url":"https://www.setn.com/News.aspx?NewsID=901595&utm_source=setn.com&utm_medium=viewall&utm_campaign=viewallnews"},{"topic":"入職2小時猝死　索賠6百萬結局曝光","dates":"02/24 14:57","url":"https://www.setn.com/News.aspx?NewsID=901581&utm_source=setn.com&utm_medium=viewall&utm_campaign=viewallnews"},{"topic":"姊妹下體都成菜花田　原因讓醫狂搖頭","dates":"02/24 13:33","url":"https://www.setn.com/News.aspx?NewsID=901508&utm_source=setn.com&utm_medium=viewall&utm_campaign=viewallnews"},{"topic":"拜登杜魯道視訊會談　合作因應中競爭","dates":"02/24 11:54","url":"https://www.setn.com/News.aspx?NewsID=901402&utm_source=setn.com&utm_medium=viewall&utm_campaign=viewallnews"},{"topic":"蓬佩奧撰文　控中共實驗室危害世界","dates":"02/24 11:50","url":"https://www.setn.com/News.aspx?NewsID=901370&utm_source=setn.com&utm_medium=viewall&utm_campaign=viewallnews"},{"topic":"日外相人權理事會發言　憂緬甸與中國","dates":"02/24 11:44","url":"https://www.setn.com/News.aspx?NewsID=901403&utm_source=setn.com&utm_medium=viewall&utm_campaign=viewallnews"},{"topic":"中國船出沒釣魚台海域　美斥蔑視規則","dates":"02/24 11:28","url":"https://www.setn.com/News.aspx?NewsID=901423&utm_source=setn.com&utm_medium=viewall&utm_campaign=viewallnews"},{"topic":"大阪等府縣解除緊急事態？26日決定","dates":"02/24 11:22","url":"https://www.setn.com/News.aspx?NewsID=901378&utm_source=setn.com&utm_medium=viewall&utm_campaign=viewallnews"},{"topic":"民主黨擬參院提案　固美關鍵科技產業","dates":"02/24 11:17","url":"https://www.setn.com/News.aspx?NewsID=901381&utm_source=setn.com&utm_medium=viewall&utm_campaign=viewallnews"},{"topic":"警站窗邊看車震！嫩妹繼續忘我激戰","dates":"02/24 10:57","url":"https://www.setn.com/News.aspx?NewsID=901430&utm_source=setn.com&utm_medium=viewall&utm_campaign=viewallnews"},{"topic":"巴西年底自行產疫苗　不依賴中國原料","dates":"02/24 10:39","url":"https://www.setn.com/News.aspx?NewsID=901369&utm_source=setn.com&utm_medium=viewall&utm_campaign=viewallnews"},{"topic":"英女王夫婿感染治療　繼續留院觀察","dates":"02/24 09:31","url":"https://www.setn.com/News.aspx?NewsID=901345&utm_source=setn.com&utm_medium=viewall&utm_campaign=viewallnews"},{"topic":"美國務院：對中政策將以競爭為主軸","dates":"02/24 09:29","url":"https://www.setn.com/News.aspx?NewsID=901346&utm_source=setn.com&utm_medium=viewall&utm_campaign=viewallnews"},{"topic":"Fed主席稱維持低利率　至經濟復甦","dates":"02/24 09:27","url":"https://www.setn.com/News.aspx?NewsID=901335&utm_source=setn.com&utm_medium=viewall&utm_campaign=viewallnews"},{"topic":"英國才宣布解禁計畫　出遊預訂數暴增","dates":"02/24 08:58","url":"https://www.setn.com/News.aspx?NewsID=901332&utm_source=setn.com&utm_medium=viewall&utm_campaign=viewallnews"},{"topic":"挪威軍方研究：軍中近半女性曾遭性騷","dates":"02/24 08:48","url":"https://www.setn.com/News.aspx?NewsID=901333&utm_source=setn.com&utm_medium=viewall&utm_campaign=viewallnews"},{"topic":"有你秘密！男勒索百名高層　結果驚人","dates":"02/24 07:00","url":"https://www.setn.com/News.aspx?NewsID=901312&utm_source=setn.com&utm_medium=viewall&utm_campaign=viewallnews"},{"topic":"美駐聯合國新大使出爐　承諾助台抗中","dates":"02/24 05:56","url":"https://www.setn.com/News.aspx?NewsID=901321&utm_source=setn.com&utm_medium=viewall&utm_campaign=viewallnews"},{"topic":"掃墓中邪？父逼她驅魔到死　醫生傻了","dates":"02/24 00:38","url":"https://www.setn.com/News.aspx?NewsID=901307&utm_source=setn.com&utm_medium=viewall&utm_campaign=viewallnews"},{"topic":"老公愛找應召妹　正宮怒開槍爆她頭","dates":"02/24 00:18","url":"https://www.setn.com/News.aspx?NewsID=900863&utm_source=setn.com&utm_medium=viewall&utm_campaign=viewallnews"}]},{"tag":"新奇","count":24,"articles":[{"topic":"華妃沒有子嗣　關鍵不是歡宜香是她","dates":"02/24 23:52","url":"https://www.setn.com/News.aspx?NewsID=901859&utm_source=setn.com&utm_medium=viewall&utm_campaign=viewallnews"},{"topic":"史上最苦命！他當皇帝三天就駕崩","dates":"02/24 22:51","url":"https://www.setn.com/News.aspx?NewsID=901851&utm_source=setn.com&utm_medium=viewall&utm_campaign=viewallnews"},{"topic":"圓明園365張照片　曝乾隆本人造像","dates":"02/24 22:14","url":"https://www.setn.com/News.aspx?NewsID=901593&utm_source=setn.com&utm_medium=viewall&utm_campaign=viewallnews"},{"topic":"金鑾殿擂台賽！他靠拳頭當上文狀元","dates":"02/24 22:00","url":"https://www.setn.com/News.aspx?NewsID=901665&utm_source=setn.com&utm_medium=viewall&utm_campaign=viewallnews"},{"topic":"古代女人偷腥下場慘　用針線縫她私處","dates":"02/24 21:09","url":"https://www.setn.com/News.aspx?NewsID=901802&utm_source=setn.com&utm_medium=viewall&utm_campaign=viewallnews"},{"topic":"為讓外孫女懷龍種　他禁止宮女這件事","dates":"02/24 21:00","url":"https://www.setn.com/News.aspx?NewsID=901716&utm_source=setn.com&utm_medium=viewall&utm_campaign=viewallnews"},{"topic":"選一款舒適沙發　測出你最能依靠的人","dates":"02/24 20:21","url":"https://www.setn.com/News.aspx?NewsID=901800&utm_source=setn.com&utm_medium=viewall&utm_campaign=viewallnews"},{"topic":"皮卡丘真存在！全身「放紅光」畫面曝","dates":"02/24 19:59","url":"https://www.setn.com/News.aspx?NewsID=901784&utm_source=setn.com&utm_medium=viewall&utm_campaign=viewallnews"},{"topic":"乾隆「香妃住處」曝光：豪華2層別墅","dates":"02/24 17:32","url":"https://www.setn.com/News.aspx?NewsID=901591&utm_source=setn.com&utm_medium=viewall&utm_campaign=viewallnews"},{"topic":"巧克力原料長這樣！網嚇：再也不敢吃","dates":"02/24 17:28","url":"https://www.setn.com/News.aspx?NewsID=901696&utm_source=setn.com&utm_medium=viewall&utm_campaign=viewallnews"},{"topic":"母鯊肚裡見驚悚人面鯊！他嗨：好兆頭","dates":"02/24 16:36","url":"https://www.setn.com/News.aspx?NewsID=901518&utm_source=setn.com&utm_medium=viewall&utm_campaign=viewallnews"},{"topic":"這55個姓氏曾誕生過皇帝　有你嗎？","dates":"02/24 15:53","url":"https://www.setn.com/News.aspx?NewsID=901564&utm_source=setn.com&utm_medium=viewall&utm_campaign=viewallnews"},{"topic":"噴86萬娶小15歲嫩妻！半年後慘了","dates":"02/24 13:48","url":"https://www.setn.com/News.aspx?NewsID=901079&utm_source=setn.com&utm_medium=viewall&utm_campaign=viewallnews"},{"topic":"意外聽尪語音訊息！她氣炸帶兒回娘家","dates":"02/24 12:53","url":"https://www.setn.com/News.aspx?NewsID=901498&utm_source=setn.com&utm_medium=viewall&utm_campaign=viewallnews"},{"topic":"因玩笑吵架！女氣到跑走　男驚孩沒了","dates":"02/24 11:21","url":"https://www.setn.com/News.aspx?NewsID=901454&utm_source=setn.com&utm_medium=viewall&utm_campaign=viewallnews"},{"topic":"元宵後！3生肖財運旺翻　伸手錢就來","dates":"02/24 08:54","url":"https://www.setn.com/News.aspx?NewsID=901350&utm_source=setn.com&utm_medium=viewall&utm_campaign=viewallnews"},{"topic":"康熙死前　為何2度點一男人陪葬？","dates":"02/24 07:59","url":"https://www.setn.com/News.aspx?NewsID=900525&utm_source=setn.com&utm_medium=viewall&utm_campaign=viewallnews"},{"topic":"張易之靠一絕招　就爽讓武則天獨寵他","dates":"02/24 07:58","url":"https://www.setn.com/News.aspx?NewsID=900594&utm_source=setn.com&utm_medium=viewall&utm_campaign=viewallnews"},{"topic":"首侍寢唐太宗　武則天就創一千古紀錄","dates":"02/24 07:57","url":"https://www.setn.com/News.aspx?NewsID=900772&utm_source=setn.com&utm_medium=viewall&utm_campaign=viewallnews"},{"topic":"他被斬前掏免死金牌　朱元璋：看清楚","dates":"02/24 07:57","url":"https://www.setn.com/News.aspx?NewsID=900932&utm_source=setn.com&utm_medium=viewall&utm_campaign=viewallnews"},{"topic":"男買錯內衣尺寸！女直接不化妝拒嫁","dates":"02/24 07:22","url":"https://www.setn.com/News.aspx?NewsID=901091&utm_source=setn.com&utm_medium=viewall&utm_campaign=viewallnews"},{"topic":"婆婆電話忘掛斷　聽到這句話媳秒崩潰","dates":"02/24 07:14","url":"https://www.setn.com/News.aspx?NewsID=901068&utm_source=setn.com&utm_medium=viewall&utm_campaign=viewallnews"},{"topic":"最變態日軍　用燒餅毒死五百名女學生","dates":"02/24 01:01","url":"https://www.setn.com/News.aspx?NewsID=901186&utm_source=setn.com&utm_medium=viewall&utm_campaign=viewallnews"},{"topic":"五虎將後代揭密　張飛72世在台灣？","dates":"02/24 00:57","url":"https://www.setn.com/News.aspx?NewsID=901313&utm_source=setn.com&utm_medium=viewall&utm_campaign=viewallnews"}]},{"tag":"社會","count":62,"articles":[{"topic":"嘉義某醫院病患遭內褲勒頸陳屍病房","dates":"02/24 23:41","url":"https://www.setn.com/News.aspx?NewsID=901673&utm_source=setn.com&utm_medium=viewall&utm_campaign=viewallnews"},{"topic":"領出鉅額現金怕搶嗎？打給110就對","dates":"02/24 23:15","url":"https://www.setn.com/News.aspx?NewsID=901853&utm_source=setn.com&utm_medium=viewall&utm_campaign=viewallnews"},{"topic":"即／民宅散發惡臭　房東開門驚見雙屍","dates":"02/24 21:57","url":"https://www.setn.com/News.aspx?NewsID=901841&utm_source=setn.com&utm_medium=viewall&utm_campaign=viewallnews"},{"topic":"火燒南陽街！網咖員工跳窗求生","dates":"02/24 21:52","url":"https://www.setn.com/News.aspx?NewsID=901767&utm_source=setn.com&utm_medium=viewall&utm_campaign=viewallnews"},{"topic":"偷吃被揭！人夫嗆：她滿足我生理需求","dates":"02/24 21:16","url":"https://www.setn.com/News.aspx?NewsID=901644&utm_source=setn.com&utm_medium=viewall&utm_campaign=viewallnews"},{"topic":"館長槍擊案外案　名錶遺失有內幕","dates":"02/24 20:44","url":"https://www.setn.com/News.aspx?NewsID=901762&utm_source=setn.com&utm_medium=viewall&utm_campaign=viewallnews"},{"topic":"北市作家熊仁謙林森北路佛堂遭潑紅漆","dates":"02/24 20:16","url":"https://www.setn.com/News.aspx?NewsID=901801&utm_source=setn.com&utm_medium=viewall&utm_campaign=viewallnews"},{"topic":"「我才是她男友！」莽男衝燒烤店打人","dates":"02/24 19:55","url":"https://www.setn.com/News.aspx?NewsID=901763&utm_source=setn.com&utm_medium=viewall&utm_campaign=viewallnews"},{"topic":"擁槍還能獲交保　黃偉哲：真讓人無奈","dates":"02/24 19:40","url":"https://www.setn.com/News.aspx?NewsID=901787&utm_source=setn.com&utm_medium=viewall&utm_campaign=viewallnews"},{"topic":"快訊／醫院命案傷勢曝！肋骨肺臟全裂","dates":"02/24 18:21","url":"https://www.setn.com/News.aspx?NewsID=901740&utm_source=setn.com&utm_medium=viewall&utm_campaign=viewallnews"},{"topic":"醉父酒駕逆向撞　1家三口父子重傷死","dates":"02/24 18:03","url":"https://www.setn.com/News.aspx?NewsID=901667&utm_source=setn.com&utm_medium=viewall&utm_campaign=viewallnews"},{"topic":"熟睡被丈夫持刀猛砍　人妻閉氣逃死劫","dates":"02/24 18:01","url":"https://www.setn.com/News.aspx?NewsID=901516&utm_source=setn.com&utm_medium=viewall&utm_campaign=viewallnews"},{"topic":"新竹騎士車禍倒臥車道　遭後車輾頭亡","dates":"02/24 17:56","url":"https://www.setn.com/News.aspx?NewsID=901697&utm_source=setn.com&utm_medium=viewall&utm_campaign=viewallnews"},{"topic":"遭愛女刺腹身亡　新莊媽苦情背景曝光","dates":"02/24 17:45","url":"https://www.setn.com/News.aspx?NewsID=901396&utm_source=setn.com&utm_medium=viewall&utm_campaign=viewallnews"},{"topic":"壓著趴牆性侵　地勤男賠70萬換緩刑","dates":"02/24 17:35","url":"https://www.setn.com/News.aspx?NewsID=901707&utm_source=setn.com&utm_medium=viewall&utm_campaign=viewallnews"},{"topic":"快訊／昔日小弟狂開16槍狠奪角頭命","dates":"02/24 17:26","url":"https://www.setn.com/News.aspx?NewsID=901702&utm_source=setn.com&utm_medium=viewall&utm_campaign=viewallnews"},{"topic":"嘿咻22次換手機　渣男試車10少女","dates":"02/24 17:02","url":"https://www.setn.com/News.aspx?NewsID=901677&utm_source=setn.com&utm_medium=viewall&utm_campaign=viewallnews"},{"topic":"苗栗重大車禍！2車對撞一家3口2死","dates":"02/24 17:00","url":"https://www.setn.com/News.aspx?NewsID=901613&utm_source=setn.com&utm_medium=viewall&utm_campaign=viewallnews"},{"topic":"酒店沒生意少爺失業　他竟改行當毒販","dates":"02/24 16:50","url":"https://www.setn.com/News.aspx?NewsID=901676&utm_source=setn.com&utm_medium=viewall&utm_campaign=viewallnews"},{"topic":"西濱車禍1分鐘追撞影片曝光　網驚呆","dates":"02/24 16:45","url":"https://www.setn.com/News.aspx?NewsID=901531&utm_source=setn.com&utm_medium=viewall&utm_campaign=viewallnews"},{"topic":"不管學運恩仇　他挺方仰寧向黑道宣戰","dates":"02/24 16:34","url":"https://www.setn.com/News.aspx?NewsID=901648&utm_source=setn.com&utm_medium=viewall&utm_campaign=viewallnews"},{"topic":"知名KTV有確診？他亂PO文下場曝","dates":"02/24 16:24","url":"https://www.setn.com/News.aspx?NewsID=901597&utm_source=setn.com&utm_medium=viewall&utm_campaign=viewallnews"},{"topic":"穿防彈衣槍斃老大　「蝦米」丟槍投案","dates":"02/24 16:10","url":"https://www.setn.com/News.aspx?NewsID=901504&utm_source=setn.com&utm_medium=viewall&utm_campaign=viewallnews"},{"topic":"寄生藍流！ 狼、禿鷹、鼠… 柯P是","dates":"02/24 15:49","url":"https://www.setn.com/News.aspx?NewsID=901606&utm_source=setn.com&utm_medium=viewall&utm_campaign=viewallnews"},{"topic":"妻要他每天睡客廳　結婚29天突消失","dates":"02/24 15:48","url":"https://www.setn.com/News.aspx?NewsID=901615&utm_source=setn.com&utm_medium=viewall&utm_campaign=viewallnews"},{"topic":"新／北市安親班空地起火上百學童逃難","dates":"02/24 15:25","url":"https://www.setn.com/News.aspx?NewsID=901601&utm_source=setn.com&utm_medium=viewall&utm_campaign=viewallnews"},{"topic":"遭女控性侵　張秉鈞：短暫交往無不法","dates":"02/24 15:23","url":"https://www.setn.com/News.aspx?NewsID=901487&utm_source=setn.com&utm_medium=viewall&utm_campaign=viewallnews"},{"topic":"聯結車翻車起火　掉鋼梁害回堵4小時","dates":"02/24 15:18","url":"https://www.setn.com/News.aspx?NewsID=901493&utm_source=setn.com&utm_medium=viewall&utm_campaign=viewallnews"},{"topic":"宜蘭驚傳遶境意外！2信徒遭爆竹炸傷","dates":"02/24 15:13","url":"https://www.setn.com/News.aspx?NewsID=901592&utm_source=setn.com&utm_medium=viewall&utm_campaign=viewallnews"},{"topic":"醉男闖機車行揮鋸　店員手臂濺血嚇壞","dates":"02/24 15:04","url":"https://www.setn.com/News.aspx?NewsID=901485&utm_source=setn.com&utm_medium=viewall&utm_campaign=viewallnews"},{"topic":"婦女節「勇氣論壇」即日起開放報名","dates":"02/24 15:00","url":"https://www.setn.com/News.aspx?NewsID=901543&utm_source=setn.com&utm_medium=viewall&utm_campaign=viewallnews"},{"topic":"台南8天2死　警政署長陳家欽坐鎮","dates":"02/24 14:58","url":"https://www.setn.com/News.aspx?NewsID=901486&utm_source=setn.com&utm_medium=viewall&utm_campaign=viewallnews"},{"topic":"看日出遭威脅　女大生掉眼鏡慘遭性侵","dates":"02/24 14:42","url":"https://www.setn.com/News.aspx?NewsID=901505&utm_source=setn.com&utm_medium=viewall&utm_campaign=viewallnews"},{"topic":"男童玩中國噴火槍遭火吻　進口商判賠","dates":"02/24 14:37","url":"https://www.setn.com/News.aspx?NewsID=901479&utm_source=setn.com&utm_medium=viewall&utm_campaign=viewallnews"},{"topic":"欲退亡友公司經營　包偉銘代愛妻出庭","dates":"02/24 14:15","url":"https://www.setn.com/News.aspx?NewsID=901532&utm_source=setn.com&utm_medium=viewall&utm_campaign=viewallnews"},{"topic":"我跟你媽拿！暴怒男刺死前女友朋友","dates":"02/24 14:06","url":"https://www.setn.com/News.aspx?NewsID=901527&utm_source=setn.com&utm_medium=viewall&utm_campaign=viewallnews"},{"topic":"2命案害慘治安　陳家欽：揪幕後黑手","dates":"02/24 13:23","url":"https://www.setn.com/News.aspx?NewsID=901506&utm_source=setn.com&utm_medium=viewall&utm_campaign=viewallnews"},{"topic":"殺警無罪改判17年　李承翰母說話了","dates":"02/24 13:15","url":"https://www.setn.com/News.aspx?NewsID=901412&utm_source=setn.com&utm_medium=viewall&utm_campaign=viewallnews"},{"topic":"凶宅裝潢轉暴漲3百萬　鄰居：該說嗎","dates":"02/24 13:02","url":"https://www.setn.com/News.aspx?NewsID=901500&utm_source=setn.com&utm_medium=viewall&utm_campaign=viewallnews"},{"topic":"上廁所竟流出精液！正妹得知真相崩潰","dates":"02/24 12:37","url":"https://www.setn.com/News.aspx?NewsID=901488&utm_source=setn.com&utm_medium=viewall&utm_campaign=viewallnews"},{"topic":"早已預謀！老大不挺怒嗆「一起死吧」","dates":"02/24 12:28","url":"https://www.setn.com/News.aspx?NewsID=901462&utm_source=setn.com&utm_medium=viewall&utm_campaign=viewallnews"},{"topic":"居檢亂跑拒繳罰單　執行官查封千萬屋","dates":"02/24 12:14","url":"https://www.setn.com/News.aspx?NewsID=901481&utm_source=setn.com&utm_medium=viewall&utm_campaign=viewallnews"},{"topic":"永和男被砍4刀　2惡煞逃亡畫面曝光","dates":"02/24 11:51","url":"https://www.setn.com/News.aspx?NewsID=901470&utm_source=setn.com&utm_medium=viewall&utm_campaign=viewallnews"},{"topic":"5所長弄獅慶生分局長　遭嘲：想升官","dates":"02/24 11:22","url":"https://www.setn.com/News.aspx?NewsID=901448&utm_source=setn.com&utm_medium=viewall&utm_campaign=viewallnews"},{"topic":"要看小姐嗎？養生館拉客拉到大白鯊","dates":"02/24 11:01","url":"https://www.setn.com/News.aspx?NewsID=901436&utm_source=setn.com&utm_medium=viewall&utm_campaign=viewallnews"},{"topic":"南陽街網咖竄火煙　警消急疏散25人","dates":"02/24 10:54","url":"https://www.setn.com/News.aspx?NewsID=901434&utm_source=setn.com&utm_medium=viewall&utm_campaign=viewallnews"},{"topic":"KANO製片爽拍3P激戰！外流全網","dates":"02/24 10:35","url":"https://www.setn.com/News.aspx?NewsID=901404&utm_source=setn.com&utm_medium=viewall&utm_campaign=viewallnews"},{"topic":"離奇墜最高大橋亡　2年前也曾發生過","dates":"02/24 10:26","url":"https://www.setn.com/News.aspx?NewsID=901418&utm_source=setn.com&utm_medium=viewall&utm_campaign=viewallnews"},{"topic":"不甩居檢開特斯拉外出！台商下場慘","dates":"02/24 10:08","url":"https://www.setn.com/News.aspx?NewsID=901383&utm_source=setn.com&utm_medium=viewall&utm_campaign=viewallnews"},{"topic":"鐵路殺警案大逆轉！原無罪改判17年","dates":"02/24 10:08","url":"https://www.setn.com/News.aspx?NewsID=901405&utm_source=setn.com&utm_medium=viewall&utm_campaign=viewallnews"},{"topic":"貨車惡意逼車還潑漆　網友起底是累犯","dates":"02/24 10:06","url":"https://www.setn.com/News.aspx?NewsID=901329&utm_source=setn.com&utm_medium=viewall&utm_campaign=viewallnews"},{"topic":"正妹學霸淫窟被搗破　賣淫價目表曝光","dates":"02/24 09:49","url":"https://www.setn.com/News.aspx?NewsID=901394&utm_source=setn.com&utm_medium=viewall&utm_campaign=viewallnews"},{"topic":"扯！8天2命案　方仰寧霸氣：戰黑道","dates":"02/24 09:46","url":"https://www.setn.com/News.aspx?NewsID=901386&utm_source=setn.com&utm_medium=viewall&utm_campaign=viewallnews"},{"topic":"學霸正妹誘賣皮肉　搶師父生意遭凌虐","dates":"02/24 08:57","url":"https://www.setn.com/News.aspx?NewsID=901367&utm_source=setn.com&utm_medium=viewall&utm_campaign=viewallnews"},{"topic":"中山高五股聯絡道　拖板車翻覆暫封路","dates":"02/24 08:35","url":"https://www.setn.com/News.aspx?NewsID=901347&utm_source=setn.com&utm_medium=viewall&utm_campaign=viewallnews"},{"topic":"控伸縮縫凸出害摔車　騎士槓北市府","dates":"02/24 08:11","url":"https://www.setn.com/News.aspx?NewsID=901330&utm_source=setn.com&utm_medium=viewall&utm_campaign=viewallnews"},{"topic":"知名製片淪A片男優　病妻乞討度日","dates":"02/24 08:08","url":"https://www.setn.com/News.aspx?NewsID=901349&utm_source=setn.com&utm_medium=viewall&utm_campaign=viewallnews"},{"topic":"「蝦米」槍殺昔日老大　臉書早預告","dates":"02/24 07:33","url":"https://www.setn.com/News.aspx?NewsID=901340&utm_source=setn.com&utm_medium=viewall&utm_campaign=viewallnews"},{"topic":"網紅「超艾夾」遭砍　主嫌10萬交保","dates":"02/24 06:47","url":"https://www.setn.com/News.aspx?NewsID=901326&utm_source=setn.com&utm_medium=viewall&utm_campaign=viewallnews"},{"topic":"維修車撞死2工班　2被告10萬交保","dates":"02/24 06:03","url":"https://www.setn.com/News.aspx?NewsID=901323&utm_source=setn.com&utm_medium=viewall&utm_campaign=viewallnews"},{"topic":"台南連環殺2死　「警中計」局長道歉","dates":"02/24 05:00","url":"https://www.setn.com/News.aspx?NewsID=901319&utm_source=setn.com&utm_medium=viewall&utm_campaign=viewallnews"},{"topic":"駭人意外　男跌入攪拌車左腳分離慘死","dates":"02/24 00:20","url":"https://www.setn.com/News.aspx?NewsID=901855&utm_source=setn.com&utm_medium=viewall&utm_campaign=viewallnews"}]},{"tag":"娛樂","count":53,"articles":[{"topic":"郭雪芙反串扮帥哥　回家洗澡都很錯愕","dates":"02/24 23:38","url":"https://star.setn.com/news/901857?utm_source=setn.com&utm_medium=viewall&utm_campaign=viewallnews"},{"topic":"甄嬛傳最心機！排名第1非甄嬛而是她","dates":"02/24 23:27","url":"https://star.setn.com/news/901630?utm_source=setn.com&utm_medium=viewall&utm_campaign=viewallnews"},{"topic":"71歲白嘉莉燒百萬住台　想買房置產","dates":"02/24 23:26","url":"https://star.setn.com/news/901854?utm_source=setn.com&utm_medium=viewall&utm_campaign=viewallnews"},{"topic":"天驕／喋血事件竟成真！母命危少東怒","dates":"02/24 23:12","url":"https://star.setn.com/news/901840?utm_source=setn.com&utm_medium=viewall&utm_campaign=viewallnews"},{"topic":"本土劇男星爆意外　被狂揍眼睛爆血管","dates":"02/24 22:56","url":"https://star.setn.com/news/901848?utm_source=setn.com&utm_medium=viewall&utm_campaign=viewallnews"},{"topic":"翁立友被憲哥嗆笨　以後出事先打給他","dates":"02/24 22:53","url":"https://star.setn.com/news/901838?utm_source=setn.com&utm_medium=viewall&utm_campaign=viewallnews"},{"topic":"跌倒眼鏡斷裂插傷鼻樑　台8男星破相","dates":"02/24 22:21","url":"https://star.setn.com/news/901839?utm_source=setn.com&utm_medium=viewall&utm_campaign=viewallnews"},{"topic":"IG頭貼放吳慷仁　他秒遭鎖：涉裸露","dates":"02/24 21:35","url":"https://star.setn.com/news/901826?utm_source=setn.com&utm_medium=viewall&utm_campaign=viewallnews"},{"topic":"8點檔女星嫁豪門　課堂老師卻成小王","dates":"02/24 21:13","url":"https://star.setn.com/news/901823?utm_source=setn.com&utm_medium=viewall&utm_campaign=viewallnews"},{"topic":"Kobe球員卡　價格曝光全場驚呆了","dates":"02/24 21:00","url":"https://star.setn.com/news/901756?utm_source=setn.com&utm_medium=viewall&utm_campaign=viewallnews"},{"topic":"青青PO出清白證據：真的沒看過本票","dates":"02/24 20:27","url":"https://star.setn.com/news/901804?utm_source=setn.com&utm_medium=viewall&utm_campaign=viewallnews"},{"topic":"女兒被霸凌不敢講　小禎心疼曝內幕","dates":"02/24 20:20","url":"https://star.setn.com/news/901736?utm_source=setn.com&utm_medium=viewall&utm_campaign=viewallnews"},{"topic":"書摘／被江宏傑氣哭　福原愛超勇敢","dates":"02/24 19:50","url":"https://star.setn.com/news/901785?utm_source=setn.com&utm_medium=viewall&utm_campaign=viewallnews"},{"topic":"被資深中醫師譴責　蒼藍鴿傻眼回應了","dates":"02/24 19:28","url":"https://star.setn.com/news/901726?utm_source=setn.com&utm_medium=viewall&utm_campaign=viewallnews"},{"topic":"加減法都不會　小馬雲證實為智力殘疾","dates":"02/24 19:21","url":"https://star.setn.com/news/901777?utm_source=setn.com&utm_medium=viewall&utm_campaign=viewallnews"},{"topic":"聽郭雪芙跳針　孫其君揪她遊吳姍儒家","dates":"02/24 19:05","url":"https://star.setn.com/news/901708?utm_source=setn.com&utm_medium=viewall&utm_campaign=viewallnews"},{"topic":"女兒狂抱女店員不肯放　他無奈曝真相","dates":"02/24 17:53","url":"https://star.setn.com/news/901568?utm_source=setn.com&utm_medium=viewall&utm_campaign=viewallnews"},{"topic":"陸女星傳隱婚阮經天？工作室聲明曝光","dates":"02/24 17:41","url":"https://star.setn.com/news/901672?utm_source=setn.com&utm_medium=viewall&utm_campaign=viewallnews"},{"topic":"被爆復合洪曉蕾　王世均甜認這關係","dates":"02/24 17:34","url":"https://star.setn.com/news/901658?utm_source=setn.com&utm_medium=viewall&utm_campaign=viewallnews"},{"topic":"雞排妹正面嬌躺照美爆　登時尚雜誌","dates":"02/24 15:49","url":"https://star.setn.com/news/901609?utm_source=setn.com&utm_medium=viewall&utm_campaign=viewallnews"},{"topic":"吳孟達肺癌傳病危　他曝星爺要出手了","dates":"02/24 15:44","url":"https://star.setn.com/news/901455?utm_source=setn.com&utm_medium=viewall&utm_campaign=viewallnews"},{"topic":"王宇婕狂出包　差點嫁給閨密尪嚇傻","dates":"02/24 15:42","url":"https://star.setn.com/news/901607?utm_source=setn.com&utm_medium=viewall&utm_campaign=viewallnews"},{"topic":"祖厝面臨拆除危機　星卉：整修要天價","dates":"02/24 15:41","url":"https://star.setn.com/news/901608?utm_source=setn.com&utm_medium=viewall&utm_campaign=viewallnews"},{"topic":"再挺歐陽娜娜　劉樂妍：本來就是祖國","dates":"02/24 15:30","url":"https://star.setn.com/news/901594?utm_source=setn.com&utm_medium=viewall&utm_campaign=viewallnews"},{"topic":"和小女友不避孕　余祥銓突拋好消息","dates":"02/24 15:25","url":"https://star.setn.com/news/901600?utm_source=setn.com&utm_medium=viewall&utm_campaign=viewallnews"},{"topic":"女星車禍昏迷100集　閨密竟嫁男友","dates":"02/24 15:11","url":"https://star.setn.com/news/901590?utm_source=setn.com&utm_medium=viewall&utm_campaign=viewallnews"},{"topic":"陽春麵不要麵是奧客？于美人說公道話","dates":"02/24 14:43","url":"https://star.setn.com/news/901567?utm_source=setn.com&utm_medium=viewall&utm_campaign=viewallnews"},{"topic":"傳婚變又沒戴婚戒　福原愛7字曝原因","dates":"02/24 14:34","url":"https://star.setn.com/news/901557?utm_source=setn.com&utm_medium=viewall&utm_campaign=viewallnews"},{"topic":"理科太太陷健康危機　停拍片轉新事業","dates":"02/24 14:22","url":"https://star.setn.com/news/901548?utm_source=setn.com&utm_medium=viewall&utm_campaign=viewallnews"},{"topic":"衛生局公文到了！罔腰限時7天內出面","dates":"02/24 14:16","url":"https://star.setn.com/news/901536?utm_source=setn.com&utm_medium=viewall&utm_campaign=viewallnews"},{"topic":"張鈞甯深夜密會男神　14年私交曝光","dates":"02/24 14:09","url":"https://star.setn.com/news/901483?utm_source=setn.com&utm_medium=viewall&utm_campaign=viewallnews"},{"topic":"余苑綺住院電燒　余天「見1幕」不捨","dates":"02/24 13:59","url":"https://star.setn.com/news/901524?utm_source=setn.com&utm_medium=viewall&utm_campaign=viewallnews"},{"topic":"遭求代言情趣玩具！劉樂妍羞：自己玩","dates":"02/24 13:40","url":"https://star.setn.com/news/901511?utm_source=setn.com&utm_medium=viewall&utm_campaign=viewallnews"},{"topic":"恐怖小三廿年殺死父母　他吐心中遺憾","dates":"02/24 13:12","url":"https://star.setn.com/news/901499?utm_source=setn.com&utm_medium=viewall&utm_campaign=viewallnews"},{"topic":"姊躲房間談戀愛　戲劇男神目睹這一幕","dates":"02/24 12:07","url":"https://star.setn.com/news/901474?utm_source=setn.com&utm_medium=viewall&utm_campaign=viewallnews"},{"topic":"吳尊10歲女國王前拉琴　家世被起底","dates":"02/24 12:06","url":"https://star.setn.com/news/901322?utm_source=setn.com&utm_medium=viewall&utm_campaign=viewallnews"},{"topic":"阮經天約拐拐泡湯　經紀人揭真實關係","dates":"02/24 11:36","url":"https://star.setn.com/news/901342?utm_source=setn.com&utm_medium=viewall&utm_campaign=viewallnews"},{"topic":"連千毅6位數找助理　看上黑澀會美眉","dates":"02/24 11:25","url":"https://star.setn.com/news/901355?utm_source=setn.com&utm_medium=viewall&utm_campaign=viewallnews"},{"topic":"隋棠認育兒錯誤　曝尪無法忍受Max","dates":"02/24 11:18","url":"https://star.setn.com/news/901388?utm_source=setn.com&utm_medium=viewall&utm_campaign=viewallnews"},{"topic":"男星爆下海當牛郎　一問原因逼哭網","dates":"02/24 11:11","url":"https://star.setn.com/news/901435?utm_source=setn.com&utm_medium=viewall&utm_campaign=viewallnews"},{"topic":"老公拍出「5月肚」　她看照片傻眼了","dates":"02/24 10:24","url":"https://star.setn.com/news/901374?utm_source=setn.com&utm_medium=viewall&utm_campaign=viewallnews"},{"topic":"《甄嬛》眉莊溫柔優雅！戲外敗壞形象","dates":"02/24 09:25","url":"https://star.setn.com/news/901376?utm_source=setn.com&utm_medium=viewall&utm_campaign=viewallnews"},{"topic":"女兒在校受委屈　陳霆直播揭心碎內幕","dates":"02/24 09:18","url":"https://star.setn.com/news/901375?utm_source=setn.com&utm_medium=viewall&utm_campaign=viewallnews"},{"topic":"表演嘉賓變選手　他曝參戰全明星心聲","dates":"02/24 09:09","url":"https://star.setn.com/news/901171?utm_source=setn.com&utm_medium=viewall&utm_campaign=viewallnews"},{"topic":"別像見最後一面！吳孟達罹癌心境曝光","dates":"02/24 08:50","url":"https://star.setn.com/news/901359?utm_source=setn.com&utm_medium=viewall&utm_campaign=viewallnews"},{"topic":"國光女神翹家進監獄　酒醉遭3人性侵","dates":"02/24 08:33","url":"https://star.setn.com/news/901351?utm_source=setn.com&utm_medium=viewall&utm_campaign=viewallnews"},{"topic":"變性懷孕0案例　罔腰男友：技術存在","dates":"02/24 08:28","url":"https://star.setn.com/news/901341?utm_source=setn.com&utm_medium=viewall&utm_campaign=viewallnews"},{"topic":"正妹收千萬斗內剩50　真相曝光大哭","dates":"02/24 08:21","url":"https://star.setn.com/news/901334?utm_source=setn.com&utm_medium=viewall&utm_campaign=viewallnews"},{"topic":"沒小孩真相曝光　驕女男神精蟲虛累累","dates":"02/24 08:00","url":"https://star.setn.com/news/901315?utm_source=setn.com&utm_medium=viewall&utm_campaign=viewallnews"},{"topic":"傳參選台北市議員　焦糖認了這1事","dates":"02/24 07:48","url":"https://star.setn.com/news/901344?utm_source=setn.com&utm_medium=viewall&utm_campaign=viewallnews"},{"topic":"阮經天爆熱戀拐拐　情人節南下見家長","dates":"02/24 07:25","url":"https://star.setn.com/news/901336?utm_source=setn.com&utm_medium=viewall&utm_campaign=viewallnews"},{"topic":"陳喬恩停工備孕？台北找醫生調養身體","dates":"02/24 06:50","url":"https://star.setn.com/news/901324?utm_source=setn.com&utm_medium=viewall&utm_campaign=viewallnews"},{"topic":"高教崩壞中？李惠仁痛揭台灣私教悲歌","dates":"02/24 00:52","url":"https://star.setn.com/news/901316?utm_source=setn.com&utm_medium=viewall&utm_campaign=viewallnews"}]},{"tag":"生活","count":121,"articles":[{"topic":"尪洗牙！女牙助一動作　網喊不單純","dates":"02/24 23:28","url":"https://www.setn.com/News.aspx?NewsID=901858&utm_source=setn.com&utm_medium=viewall&utm_campaign=viewallnews"},{"topic":"3大燈會順延　哪裡賞燈成元宵課題","dates":"02/24 22:36","url":"https://www.setn.com/News.aspx?NewsID=901782&utm_source=setn.com&utm_medium=viewall&utm_campaign=viewallnews"},{"topic":"胸口草莓被男友發現　劈腿女2字騙過","dates":"02/24 22:33","url":"https://www.setn.com/News.aspx?NewsID=901846&utm_source=setn.com&utm_medium=viewall&utm_campaign=viewallnews"},{"topic":"喝湯驚見「瓜仔有臉」　網：不要吃它","dates":"02/24 22:29","url":"https://www.setn.com/News.aspx?NewsID=901699&utm_source=setn.com&utm_medium=viewall&utm_campaign=viewallnews"},{"topic":"肌膚急救神物！超強玻尿酸讓肌膚爆水","dates":"02/24 22:27","url":"https://www.setn.com/News.aspx?NewsID=901835&utm_source=setn.com&utm_medium=viewall&utm_campaign=viewallnews"},{"topic":"年收2百萬該去？網嘆一看地點卻搖頭","dates":"02/24 22:02","url":"https://www.setn.com/News.aspx?NewsID=901843&utm_source=setn.com&utm_medium=viewall&utm_campaign=viewallnews"},{"topic":"兒脫褲逼看屁屁有沒有擦乾淨　母崩潰","dates":"02/24 21:47","url":"https://www.setn.com/News.aspx?NewsID=901836&utm_source=setn.com&utm_medium=viewall&utm_campaign=viewallnews"},{"topic":"年輕人面試遭老闆趕　他一句話神反轉","dates":"02/24 21:43","url":"https://www.setn.com/News.aspx?NewsID=901834&utm_source=setn.com&utm_medium=viewall&utm_campaign=viewallnews"},{"topic":"摘星料理到街頭小吃　高麗菜變化多！","dates":"02/24 21:40","url":"https://www.setn.com/News.aspx?NewsID=901771&utm_source=setn.com&utm_medium=viewall&utm_campaign=viewallnews"},{"topic":"戀愛理論大師出沒校園　問他們準沒錯","dates":"02/24 21:26","url":"https://www.setn.com/News.aspx?NewsID=901796&utm_source=setn.com&utm_medium=viewall&utm_campaign=viewallnews"},{"topic":"虎爺降世直挺坐神桌　網友笑：無違和","dates":"02/24 21:15","url":"https://www.setn.com/News.aspx?NewsID=901825&utm_source=setn.com&utm_medium=viewall&utm_campaign=viewallnews"},{"topic":"人妻懷了第8胎　渣夫不戴套逼墮4胎","dates":"02/24 21:13","url":"https://www.setn.com/News.aspx?NewsID=901636&utm_source=setn.com&utm_medium=viewall&utm_campaign=viewallnews"},{"topic":"搶救神佛！用傳統工藝回復神明風采","dates":"02/24 21:13","url":"https://www.setn.com/News.aspx?NewsID=901808&utm_source=setn.com&utm_medium=viewall&utm_campaign=viewallnews"},{"topic":"連假又變天　吳德榮曝好天氣時間","dates":"02/24 21:11","url":"https://www.setn.com/News.aspx?NewsID=901818&utm_source=setn.com&utm_medium=viewall&utm_campaign=viewallnews"},{"topic":"酸辣湯沒香菜給負評！店家傻：只有蔥","dates":"02/24 21:10","url":"https://www.setn.com/News.aspx?NewsID=901769&utm_source=setn.com&utm_medium=viewall&utm_campaign=viewallnews"},{"topic":"哪條牛仔褲破萬？　答案公布網傻眼","dates":"02/24 21:09","url":"https://www.setn.com/News.aspx?NewsID=901821&utm_source=setn.com&utm_medium=viewall&utm_campaign=viewallnews"},{"topic":"高麗菜價格狂跌　4萬顆免費供採","dates":"02/24 21:05","url":"https://www.setn.com/News.aspx?NewsID=901770&utm_source=setn.com&utm_medium=viewall&utm_campaign=viewallnews"},{"topic":"連假注意3地雷路段　尖峰時段出爐","dates":"02/24 21:04","url":"https://www.setn.com/News.aspx?NewsID=901806&utm_source=setn.com&utm_medium=viewall&utm_campaign=viewallnews"},{"topic":"外送餐點驚見臉照　竟是「鄉民女神」","dates":"02/24 20:45","url":"https://www.setn.com/News.aspx?NewsID=901812&utm_source=setn.com&utm_medium=viewall&utm_campaign=viewallnews"},{"topic":"小米手環顯示1錯別字　男嘆：很受傷","dates":"02/24 20:42","url":"https://www.setn.com/News.aspx?NewsID=901807&utm_source=setn.com&utm_medium=viewall&utm_campaign=viewallnews"},{"topic":"袁世凱用了1計　讓末代晚清徹底覆亡","dates":"02/24 20:35","url":"https://www.setn.com/News.aspx?NewsID=901575&utm_source=setn.com&utm_medium=viewall&utm_campaign=viewallnews"},{"topic":"大玩創意吃法！嘉義烏金迸鹹甜好滋味","dates":"02/24 20:26","url":"https://www.setn.com/News.aspx?NewsID=901745&utm_source=setn.com&utm_medium=viewall&utm_campaign=viewallnews"},{"topic":"此人遭蔣介石排擠　宋美齡更要他的命","dates":"02/24 20:22","url":"https://www.setn.com/News.aspx?NewsID=901565&utm_source=setn.com&utm_medium=viewall&utm_campaign=viewallnews"},{"topic":"電費比夏天貴？網揭冬季「吃電怪獸」","dates":"02/24 20:02","url":"https://www.setn.com/News.aspx?NewsID=901791&utm_source=setn.com&utm_medium=viewall&utm_campaign=viewallnews"},{"topic":"元宵拼特色！各地饕客口袋名單大公開","dates":"02/24 19:48","url":"https://www.setn.com/News.aspx?NewsID=901753&utm_source=setn.com&utm_medium=viewall&utm_campaign=viewallnews"},{"topic":"泰女被男友騙「胸下刺3字」台人看傻","dates":"02/24 19:42","url":"https://www.setn.com/News.aspx?NewsID=901795&utm_source=setn.com&utm_medium=viewall&utm_campaign=viewallnews"},{"topic":"大馬爆非洲豬瘟　攜豬肉入境罰20萬","dates":"02/24 19:40","url":"https://www.setn.com/News.aspx?NewsID=901790&utm_source=setn.com&utm_medium=viewall&utm_campaign=viewallnews"},{"topic":"今年財位在西方　２要點助你財運爆棚","dates":"02/24 19:03","url":"https://www.setn.com/News.aspx?NewsID=901758&utm_source=setn.com&utm_medium=viewall&utm_campaign=viewallnews"},{"topic":"冷凍魚怎煮才好吃？內行揭0失敗做法","dates":"02/24 18:59","url":"https://www.setn.com/News.aspx?NewsID=901744&utm_source=setn.com&utm_medium=viewall&utm_campaign=viewallnews"},{"topic":"五星飯店住一晚　第三人加30就能住","dates":"02/24 18:44","url":"https://www.setn.com/News.aspx?NewsID=901760&utm_source=setn.com&utm_medium=viewall&utm_campaign=viewallnews"},{"topic":"台灣治安為何遠勝歐美？網點出一關鍵","dates":"02/24 18:41","url":"https://www.setn.com/News.aspx?NewsID=901752&utm_source=setn.com&utm_medium=viewall&utm_campaign=viewallnews"},{"topic":"香腸怎麼煎才不會焦？內行曝簡單1招","dates":"02/24 18:40","url":"https://www.setn.com/News.aspx?NewsID=901530&utm_source=setn.com&utm_medium=viewall&utm_campaign=viewallnews"},{"topic":"婆婆帶6人闖娘家吃年夜飯　險全武行","dates":"02/24 18:31","url":"https://www.setn.com/News.aspx?NewsID=901747&utm_source=setn.com&utm_medium=viewall&utm_campaign=viewallnews"},{"topic":"男騎士環島！背牌8字揭原因　網心疼","dates":"02/24 18:16","url":"https://www.setn.com/News.aspx?NewsID=901733&utm_source=setn.com&utm_medium=viewall&utm_campaign=viewallnews"},{"topic":"7、8年級生差在哪？網點出抑鬱關鍵","dates":"02/24 18:12","url":"https://www.setn.com/News.aspx?NewsID=901722&utm_source=setn.com&utm_medium=viewall&utm_campaign=viewallnews"},{"topic":"豬腳怎滷才香Ｑ？加1物逼出黏稠膠質","dates":"02/24 18:10","url":"https://www.setn.com/News.aspx?NewsID=901549&utm_source=setn.com&utm_medium=viewall&utm_campaign=viewallnews"},{"topic":"她做年糕回娘家：犯忌諱　網驚沒聽過","dates":"02/24 18:05","url":"https://www.setn.com/News.aspx?NewsID=901573&utm_source=setn.com&utm_medium=viewall&utm_campaign=viewallnews"},{"topic":"影／爸爸的手指轉盤　1招逼睡2兒","dates":"02/24 18:04","url":"https://www.setn.com/News.aspx?NewsID=901728&utm_source=setn.com&utm_medium=viewall&utm_campaign=viewallnews"},{"topic":"懷7胎墮4嬰！渣夫逼流產　她求別拿","dates":"02/24 17:55","url":"https://www.setn.com/News.aspx?NewsID=901723&utm_source=setn.com&utm_medium=viewall&utm_campaign=viewallnews"},{"topic":"買85元便當3主菜塞爆　結局神反轉","dates":"02/24 17:42","url":"https://www.setn.com/News.aspx?NewsID=901706&utm_source=setn.com&utm_medium=viewall&utm_campaign=viewallnews"},{"topic":"全聯咖啡豆升級　喝一杯超商價7折","dates":"02/24 17:34","url":"https://www.setn.com/News.aspx?NewsID=901691&utm_source=setn.com&utm_medium=viewall&utm_campaign=viewallnews"},{"topic":"大溪秘境／郊山小百岳　遠眺石門水庫","dates":"02/24 17:34","url":"https://www.setn.com/News.aspx?NewsID=901694&utm_source=setn.com&utm_medium=viewall&utm_campaign=viewallnews"},{"topic":"女僕咖啡不只賣萌　徵選條件需３能力","dates":"02/24 17:27","url":"https://www.setn.com/News.aspx?NewsID=901698&utm_source=setn.com&utm_medium=viewall&utm_campaign=viewallnews"},{"topic":"起薪最佳大學　這校40K與台大齊名","dates":"02/24 17:22","url":"https://www.setn.com/News.aspx?NewsID=901690&utm_source=setn.com&utm_medium=viewall&utm_campaign=viewallnews"},{"topic":"到職第1天前輩吐這句　全場勸：快逃","dates":"02/24 17:21","url":"https://www.setn.com/News.aspx?NewsID=901533&utm_source=setn.com&utm_medium=viewall&utm_campaign=viewallnews"},{"topic":"武肺疫苗恐有副作用？張上淳：機率低","dates":"02/24 17:20","url":"https://www.setn.com/News.aspx?NewsID=901685&utm_source=setn.com&utm_medium=viewall&utm_campaign=viewallnews"},{"topic":"全國佔比最高！薇閣學測滿級分11人","dates":"02/24 17:15","url":"https://www.setn.com/News.aspx?NewsID=901693&utm_source=setn.com&utm_medium=viewall&utm_campaign=viewallnews"},{"topic":"夫妻床組用粉紅色會偷吃？網一句破解","dates":"02/24 17:14","url":"https://www.setn.com/News.aspx?NewsID=901655&utm_source=setn.com&utm_medium=viewall&utm_campaign=viewallnews"},{"topic":"煮蝦先挑「背部黑線」？網曝驚人差異","dates":"02/24 16:54","url":"https://www.setn.com/News.aspx?NewsID=901675&utm_source=setn.com&utm_medium=viewall&utm_campaign=viewallnews"},{"topic":"少子化衝擊！台灣觀光學院將全面停招","dates":"02/24 16:53","url":"https://www.setn.com/News.aspx?NewsID=901651&utm_source=setn.com&utm_medium=viewall&utm_campaign=viewallnews"},{"topic":"水桶裝硬幣換鈔遭拒？銀行：是誤會","dates":"02/24 16:50","url":"https://www.setn.com/News.aspx?NewsID=901642&utm_source=setn.com&utm_medium=viewall&utm_campaign=viewallnews"},{"topic":"平價牛排點幾分熟？網驚：吃錯20年","dates":"02/24 16:46","url":"https://www.setn.com/News.aspx?NewsID=901639&utm_source=setn.com&utm_medium=viewall&utm_campaign=viewallnews"},{"topic":"最狠心「5星座」！分手不再是朋友","dates":"02/24 16:42","url":"https://www.setn.com/News.aspx?NewsID=901647&utm_source=setn.com&utm_medium=viewall&utm_campaign=viewallnews"},{"topic":"最美「紫爆」來襲！古亭花海成打卡點","dates":"02/24 16:40","url":"https://www.setn.com/News.aspx?NewsID=901656&utm_source=setn.com&utm_medium=viewall&utm_campaign=viewallnews"},{"topic":"性感女業務拉保險！襯衫釦全開曬長輩","dates":"02/24 15:59","url":"https://www.setn.com/News.aspx?NewsID=901619&utm_source=setn.com&utm_medium=viewall&utm_campaign=viewallnews"},{"topic":"熱炒店白飯免費　奧客整鍋端走傻眼了","dates":"02/24 15:57","url":"https://www.setn.com/News.aspx?NewsID=901610&utm_source=setn.com&utm_medium=viewall&utm_campaign=viewallnews"},{"topic":"維生素C多3倍　哪1色甜椒最厲害？","dates":"02/24 15:54","url":"https://www.setn.com/News.aspx?NewsID=901545&utm_source=setn.com&utm_medium=viewall&utm_campaign=viewallnews"},{"topic":"零錢箱冒2萬元千鈔！店員：是回收伯","dates":"02/24 15:50","url":"https://www.setn.com/News.aspx?NewsID=901528&utm_source=setn.com&utm_medium=viewall&utm_campaign=viewallnews"},{"topic":"女帶「兩大草莓」見男友！網傻：糟糕","dates":"02/24 15:38","url":"https://www.setn.com/News.aspx?NewsID=901605&utm_source=setn.com&utm_medium=viewall&utm_campaign=viewallnews"},{"topic":"嗆客「耳朵長包皮」鴨肉飯翻版回應了","dates":"02/24 15:35","url":"https://www.setn.com/News.aspx?NewsID=901377&utm_source=setn.com&utm_medium=viewall&utm_campaign=viewallnews"},{"topic":"盛唐中毒再一樁！台中男疑服雄黃重傷","dates":"02/24 15:24","url":"https://www.setn.com/News.aspx?NewsID=901555&utm_source=setn.com&utm_medium=viewall&utm_campaign=viewallnews"},{"topic":"友還錢給截圖證明　他等嘸入帳驚有詭","dates":"02/24 15:18","url":"https://www.setn.com/News.aspx?NewsID=901572&utm_source=setn.com&utm_medium=viewall&utm_campaign=viewallnews"},{"topic":"建中生：台大沒比較好　呂秋遠憶當年","dates":"02/24 15:14","url":"https://www.setn.com/News.aspx?NewsID=901586&utm_source=setn.com&utm_medium=viewall&utm_campaign=viewallnews"},{"topic":"做完正顎拜訪親戚　表姐反應笑翻網","dates":"02/24 15:06","url":"https://www.setn.com/News.aspx?NewsID=901534&utm_source=setn.com&utm_medium=viewall&utm_campaign=viewallnews"},{"topic":"不斷更新／境外＋4！自美、馬國入境","dates":"02/24 15:05","url":"https://www.setn.com/News.aspx?NewsID=901577&utm_source=setn.com&utm_medium=viewall&utm_campaign=viewallnews"},{"topic":"20萬劑AZ疫苗遲到了？陳時中回應","dates":"02/24 15:04","url":"https://www.setn.com/News.aspx?NewsID=901588&utm_source=setn.com&utm_medium=viewall&utm_campaign=viewallnews"},{"topic":"基層醫護提2訴求　李伯璋接下陳情書","dates":"02/24 15:00","url":"https://www.setn.com/News.aspx?NewsID=901473&utm_source=setn.com&utm_medium=viewall&utm_campaign=viewallnews"},{"topic":"學測數學難！滿級分人數10年最低","dates":"02/24 15:00","url":"https://www.setn.com/News.aspx?NewsID=901589&utm_source=setn.com&utm_medium=viewall&utm_campaign=viewallnews"},{"topic":"元宵別忘了拜地基主　護佑家宅全年旺","dates":"02/24 14:55","url":"https://www.setn.com/News.aspx?NewsID=901541&utm_source=setn.com&utm_medium=viewall&utm_campaign=viewallnews"},{"topic":"為何韓國變超強？1關鍵曝：台灣輸了","dates":"02/24 14:51","url":"https://www.setn.com/News.aspx?NewsID=901562&utm_source=setn.com&utm_medium=viewall&utm_campaign=viewallnews"},{"topic":"228連假比照春節　高鐵無自由座","dates":"02/24 14:50","url":"https://www.setn.com/News.aspx?NewsID=901495&utm_source=setn.com&utm_medium=viewall&utm_campaign=viewallnews"},{"topic":"疫苗接種勿略一線人員家屬！阿中回應","dates":"02/24 14:46","url":"https://www.setn.com/News.aspx?NewsID=901569&utm_source=setn.com&utm_medium=viewall&utm_campaign=viewallnews"},{"topic":"準岳母要百萬聘金！再開2條件他崩潰","dates":"02/24 14:43","url":"https://www.setn.com/News.aspx?NewsID=901542&utm_source=setn.com&utm_medium=viewall&utm_campaign=viewallnews"},{"topic":"防疫花燈是鳳梨網嚇壞！醫勸別想太多","dates":"02/24 14:39","url":"https://www.setn.com/News.aspx?NewsID=901496&utm_source=setn.com&utm_medium=viewall&utm_campaign=viewallnews"},{"topic":"學測落點預估　台大醫60級分才過關","dates":"02/24 14:31","url":"https://www.setn.com/News.aspx?NewsID=901550&utm_source=setn.com&utm_medium=viewall&utm_campaign=viewallnews"},{"topic":"國台辦釋千萬疫苗含台灣　陳時中回應","dates":"02/24 14:25","url":"https://www.setn.com/News.aspx?NewsID=901551&utm_source=setn.com&utm_medium=viewall&utm_campaign=viewallnews"},{"topic":"元宵節搭小黃猜燈謎　搶拿限量乘車金","dates":"02/24 14:25","url":"https://www.setn.com/News.aspx?NewsID=901552&utm_source=setn.com&utm_medium=viewall&utm_campaign=viewallnews"},{"topic":"歷史上的今天／台首位卡奴破產免還債","dates":"02/24 14:24","url":"https://www.setn.com/News.aspx?NewsID=901482&utm_source=setn.com&utm_medium=viewall&utm_campaign=viewallnews"},{"topic":"男大口喝水！女友見狀「吐1句」崩潰","dates":"02/24 14:14","url":"https://www.setn.com/News.aspx?NewsID=901501&utm_source=setn.com&utm_medium=viewall&utm_campaign=viewallnews"},{"topic":"3月起開放國際醫療　陳時中：5要件","dates":"02/24 14:13","url":"https://www.setn.com/News.aspx?NewsID=901535&utm_source=setn.com&utm_medium=viewall&utm_campaign=viewallnews"},{"topic":"3月起入境鬆綁　部分國家可縮短居檢","dates":"02/24 14:13","url":"https://www.setn.com/News.aspx?NewsID=901540&utm_source=setn.com&utm_medium=viewall&utm_campaign=viewallnews"},{"topic":"陳時中：3／1起恢復外國人入境轉機","dates":"02/24 14:11","url":"https://www.setn.com/News.aspx?NewsID=901539&utm_source=setn.com&utm_medium=viewall&utm_campaign=viewallnews"},{"topic":"境外＋4都曾確診過！自美、馬國入境","dates":"02/24 14:05","url":"https://www.setn.com/News.aspx?NewsID=901490&utm_source=setn.com&utm_medium=viewall&utm_campaign=viewallnews"},{"topic":"無薪假4千人　邊境管制為主要影響","dates":"02/24 13:23","url":"https://www.setn.com/News.aspx?NewsID=901450&utm_source=setn.com&utm_medium=viewall&utm_campaign=viewallnews"},{"topic":"爬山遲到13分沒飯吃？母怨不近人情","dates":"02/24 12:52","url":"https://www.setn.com/News.aspx?NewsID=901489&utm_source=setn.com&utm_medium=viewall&utm_campaign=viewallnews"},{"topic":"櫃姐爆百貨限戴淡口罩　總公司反駁","dates":"02/24 12:47","url":"https://www.setn.com/News.aspx?NewsID=901453&utm_source=setn.com&utm_medium=viewall&utm_campaign=viewallnews"},{"topic":"健保調部分負擔影響7成人？仍待核定","dates":"02/24 12:39","url":"https://www.setn.com/News.aspx?NewsID=901491&utm_source=setn.com&utm_medium=viewall&utm_campaign=viewallnews"},{"topic":"先炒番茄還炒蛋？內行人曝失敗關鍵","dates":"02/24 12:30","url":"https://www.setn.com/News.aspx?NewsID=901424&utm_source=setn.com&utm_medium=viewall&utm_campaign=viewallnews"},{"topic":"111學測擬考3天　命題方向一次看","dates":"02/24 11:58","url":"https://www.setn.com/News.aspx?NewsID=901472&utm_source=setn.com&utm_medium=viewall&utm_campaign=viewallnews"},{"topic":"醫療工會揭盲點！籲健保會代表納勞工","dates":"02/24 11:36","url":"https://www.setn.com/News.aspx?NewsID=901415&utm_source=setn.com&utm_medium=viewall&utm_campaign=viewallnews"},{"topic":"學測數學五標下滑　大考中心曝2關鍵","dates":"02/24 11:27","url":"https://www.setn.com/News.aspx?NewsID=901461&utm_source=setn.com&utm_medium=viewall&utm_campaign=viewallnews"},{"topic":"引矚目！明星現身妙天禪師祈福團拜","dates":"02/24 11:08","url":"https://www.setn.com/News.aspx?NewsID=901442&utm_source=setn.com&utm_medium=viewall&utm_campaign=viewallnews"},{"topic":"元宵節不只吃湯圓！「這樣做」旺整年","dates":"02/24 11:07","url":"https://www.setn.com/News.aspx?NewsID=901441&utm_source=setn.com&utm_medium=viewall&utm_campaign=viewallnews"},{"topic":"祭親民價　Gogoro搶進大眾市場","dates":"02/24 11:00","url":"https://www.setn.com/News.aspx?NewsID=901406&utm_source=setn.com&utm_medium=viewall&utm_campaign=viewallnews"},{"topic":"爸逼房內裝監視！隱私全露男大生崩潰","dates":"02/24 10:53","url":"https://www.setn.com/News.aspx?NewsID=901397&utm_source=setn.com&utm_medium=viewall&utm_campaign=viewallnews"},{"topic":"威力彩衝7.2億　6生肖牛年變富翁","dates":"02/24 10:48","url":"https://www.setn.com/News.aspx?NewsID=901431&utm_source=setn.com&utm_medium=viewall&utm_campaign=viewallnews"},{"topic":"他1年住50間！10大最佳飯店曝光","dates":"02/24 10:46","url":"https://www.setn.com/News.aspx?NewsID=901433&utm_source=setn.com&utm_medium=viewall&utm_campaign=viewallnews"},{"topic":"台灣防疫成效亮眼　登瑞典電視台","dates":"02/24 10:44","url":"https://www.setn.com/News.aspx?NewsID=901379&utm_source=setn.com&utm_medium=viewall&utm_campaign=viewallnews"},{"topic":"七年級是最慘世代？網揭真相：沒爽到","dates":"02/24 10:37","url":"https://www.setn.com/News.aspx?NewsID=901385&utm_source=setn.com&utm_medium=viewall&utm_campaign=viewallnews"},{"topic":"華航空中女王告別　最後飛行時間確定","dates":"02/24 10:36","url":"https://www.setn.com/News.aspx?NewsID=901422&utm_source=setn.com&utm_medium=viewall&utm_campaign=viewallnews"},{"topic":"屬牛99元！228全台樂園優惠一覽","dates":"02/24 10:34","url":"https://www.setn.com/News.aspx?NewsID=901413&utm_source=setn.com&utm_medium=viewall&utm_campaign=viewallnews"},{"topic":"男加分上醫學系！網曝1後果：最悲劇","dates":"02/24 10:22","url":"https://www.setn.com/News.aspx?NewsID=901372&utm_source=setn.com&utm_medium=viewall&utm_campaign=viewallnews"},{"topic":"獨／盛唐鉛中毒！廢照名醫傳改名解套","dates":"02/24 10:13","url":"https://www.setn.com/News.aspx?NewsID=901408&utm_source=setn.com&utm_medium=viewall&utm_campaign=viewallnews"},{"topic":"能再＋0？國門重啟？阿中14時說明","dates":"02/24 10:04","url":"https://www.setn.com/News.aspx?NewsID=901401&utm_source=setn.com&utm_medium=viewall&utm_campaign=viewallnews"},{"topic":"萬的部首不是艸！正解曝眾驚：學錯？","dates":"02/24 09:55","url":"https://www.setn.com/News.aspx?NewsID=901362&utm_source=setn.com&utm_medium=viewall&utm_campaign=viewallnews"},{"topic":"學測五標一覽！數學頂標創4年新低","dates":"02/24 09:51","url":"https://www.setn.com/News.aspx?NewsID=901393&utm_source=setn.com&utm_medium=viewall&utm_campaign=viewallnews"},{"topic":"流產3次還罹癌！公婆打包她行李趕人","dates":"02/24 09:43","url":"https://www.setn.com/News.aspx?NewsID=901368&utm_source=setn.com&utm_medium=viewall&utm_campaign=viewallnews"},{"topic":"台南人「下次約吃飯」　釣出市長認證","dates":"02/24 09:31","url":"https://www.setn.com/News.aspx?NewsID=901371&utm_source=setn.com&utm_medium=viewall&utm_campaign=viewallnews"},{"topic":"男友突問：當小老婆好嗎　原因嚇壞她","dates":"02/24 09:31","url":"https://www.setn.com/News.aspx?NewsID=901380&utm_source=setn.com&utm_medium=viewall&utm_campaign=viewallnews"},{"topic":"艾菲爾：5大星座「晚婚更幸福」","dates":"02/24 09:17","url":"https://www.setn.com/News.aspx?NewsID=901373&utm_source=setn.com&utm_medium=viewall&utm_campaign=viewallnews"},{"topic":"他曝韓國要跟台灣學的4事　引網熱議","dates":"02/24 09:00","url":"https://www.setn.com/News.aspx?NewsID=901060&utm_source=setn.com&utm_medium=viewall&utm_campaign=viewallnews"},{"topic":"她傳給外送員「7字」老公一看不爽了","dates":"02/24 08:29","url":"https://www.setn.com/News.aspx?NewsID=901343&utm_source=setn.com&utm_medium=viewall&utm_campaign=viewallnews"},{"topic":"難產！尪狂問「保險給付嗎」人妻心碎","dates":"02/24 08:21","url":"https://www.setn.com/News.aspx?NewsID=901348&utm_source=setn.com&utm_medium=viewall&utm_campaign=viewallnews"},{"topic":"大學學測成績9時出爐　查詢看這裡","dates":"02/24 07:30","url":"https://www.setn.com/News.aspx?NewsID=901310&utm_source=setn.com&utm_medium=viewall&utm_campaign=viewallnews"},{"topic":"更強冷空氣襲時間曝光　3月恐倒春寒","dates":"02/24 07:25","url":"https://www.setn.com/News.aspx?NewsID=901337&utm_source=setn.com&utm_medium=viewall&utm_campaign=viewallnews"},{"topic":"住廟附近會被保庇？命理師：其實更衰","dates":"02/24 07:10","url":"https://www.setn.com/News.aspx?NewsID=901009&utm_source=setn.com&utm_medium=viewall&utm_campaign=viewallnews"},{"topic":"知名便當店嗆「耳朵長包皮」女客氣炸","dates":"02/24 07:00","url":"https://www.setn.com/News.aspx?NewsID=901317&utm_source=setn.com&utm_medium=viewall&utm_campaign=viewallnews"},{"topic":"今高溫29度　228連假先濕冷轉晴","dates":"02/24 06:56","url":"https://www.setn.com/News.aspx?NewsID=901325&utm_source=setn.com&utm_medium=viewall&utm_campaign=viewallnews"},{"topic":"別再豆漿配油條　營養師：這組合更好","dates":"02/24 06:06","url":"https://www.setn.com/News.aspx?NewsID=901268&utm_source=setn.com&utm_medium=viewall&utm_campaign=viewallnews"},{"topic":"丫鬟給少爺洗腳被看上！生子舉世聞名","dates":"02/24 01:08","url":"https://www.setn.com/News.aspx?NewsID=901318&utm_source=setn.com&utm_medium=viewall&utm_campaign=viewallnews"},{"topic":"朱元璋宴請功臣　劉伯溫看菜色冒冷汗","dates":"02/24 00:35","url":"https://www.setn.com/News.aspx?NewsID=901314&utm_source=setn.com&utm_medium=viewall&utm_campaign=viewallnews"}]},{"tag":"汽車","count":10,"articles":[{"topic":"越野玩家流口水　美軍訂購新型戰術車","dates":"02/24 22:48","url":"https://www.setn.com/News.aspx?NewsID=901850&utm_source=setn.com&utm_medium=viewall&utm_campaign=viewallnews"},{"topic":"現代發表全新電動休旅　車內空間驚人","dates":"02/24 21:27","url":"https://www.setn.com/News.aspx?NewsID=901525&utm_source=setn.com&utm_medium=viewall&utm_campaign=viewallnews"},{"topic":"豐田繪畫大賽　創下台灣兒童繪畫紀錄","dates":"02/24 21:00","url":"https://www.setn.com/News.aspx?NewsID=901633&utm_source=setn.com&utm_medium=viewall&utm_campaign=viewallnews"},{"topic":"福斯密謀　讓保時捷變吸鈔機","dates":"02/24 20:21","url":"https://www.setn.com/News.aspx?NewsID=900815&utm_source=setn.com&utm_medium=viewall&utm_campaign=viewallnews"},{"topic":"科技全面提升　賓士新一代C系列發表","dates":"02/24 19:46","url":"https://www.setn.com/News.aspx?NewsID=901456&utm_source=setn.com&utm_medium=viewall&utm_campaign=viewallnews"},{"topic":"想體驗油電車　用租的也可以","dates":"02/24 17:00","url":"https://www.setn.com/News.aspx?NewsID=900885&utm_source=setn.com&utm_medium=viewall&utm_campaign=viewallnews"},{"topic":"Swift冠軍特仕　全球限量推出","dates":"02/24 15:00","url":"https://www.setn.com/News.aspx?NewsID=901502&utm_source=setn.com&utm_medium=viewall&utm_campaign=viewallnews"},{"topic":"納智捷健康科技　讓你多活10年","dates":"02/24 15:00","url":"https://www.setn.com/News.aspx?NewsID=901558&utm_source=setn.com&utm_medium=viewall&utm_campaign=viewallnews"},{"topic":"慘賠504萬　籃球之神愛車拍賣","dates":"02/24 12:17","url":"https://www.setn.com/News.aspx?NewsID=900397&utm_source=setn.com&utm_medium=viewall&utm_campaign=viewallnews"},{"topic":"越南國產豪車　開價500萬台幣","dates":"02/24 08:42","url":"https://www.setn.com/News.aspx?NewsID=901363&utm_source=setn.com&utm_medium=viewall&utm_campaign=viewallnews"}]},{"tag":"音樂","count":6,"articles":[{"topic":"前寶塚歌劇團員新秀　免去日本也能看","dates":"02/24 22:00","url":"https://star.setn.com/news/901556?utm_source=setn.com&utm_medium=viewall&utm_campaign=viewallnews"},{"topic":"8年前無預警休團　棉花糖曝新近況","dates":"02/24 20:00","url":"https://star.setn.com/news/901509?utm_source=setn.com&utm_medium=viewall&utm_campaign=viewallnews"},{"topic":"玉女歌手曝交往條件　陳美鳳一句虧爆","dates":"02/24 18:43","url":"https://star.setn.com/news/901584?utm_source=setn.com&utm_medium=viewall&utm_campaign=viewallnews"},{"topic":"林明禎爽拿台灣健保卡　曝絕美證件照","dates":"02/24 18:20","url":"https://star.setn.com/news/901710?utm_source=setn.com&utm_medium=viewall&utm_campaign=viewallnews"},{"topic":"KKBOX風雲榜卡司曝光30組接力","dates":"02/24 18:09","url":"https://star.setn.com/news/901570?utm_source=setn.com&utm_medium=viewall&utm_campaign=viewallnews"},{"topic":"親自將夥伴炸粉碎！法電音傳奇傳解散","dates":"02/24 16:11","url":"https://star.setn.com/news/901623?utm_source=setn.com&utm_medium=viewall&utm_campaign=viewallnews"}]},{"tag":"科技","count":7,"articles":[{"topic":"台灣團隊提出新電極架構　登國際期刊","dates":"02/24 21:39","url":"https://www.setn.com/News.aspx?NewsID=901792&utm_source=setn.com&utm_medium=viewall&utm_campaign=viewallnews"},{"topic":"科技公司遭駭　微軟：至少出動千人","dates":"02/24 17:00","url":"https://www.setn.com/News.aspx?NewsID=901653&utm_source=setn.com&utm_medium=viewall&utm_campaign=viewallnews"},{"topic":"頂規愛瘋12太大一支！她怨不如i7","dates":"02/24 14:10","url":"https://www.setn.com/News.aspx?NewsID=901526&utm_source=setn.com&utm_medium=viewall&utm_campaign=viewallnews"},{"topic":"HTC專利贏！中國廠商賠1500萬","dates":"02/24 13:46","url":"https://www.setn.com/News.aspx?NewsID=901513&utm_source=setn.com&utm_medium=viewall&utm_campaign=viewallnews"},{"topic":"迎接新學年！三星平板推星霧藍新色","dates":"02/24 11:52","url":"https://www.setn.com/News.aspx?NewsID=901466&utm_source=setn.com&utm_medium=viewall&utm_campaign=viewallnews"},{"topic":"當心！谷歌推播Falsh更新假的","dates":"02/24 11:11","url":"https://www.setn.com/News.aspx?NewsID=901437&utm_source=setn.com&utm_medium=viewall&utm_campaign=viewallnews"},{"topic":"澳洲和臉書槓上　為何全世界都在看？","dates":"02/24 07:29","url":"https://www.setn.com/News.aspx?NewsID=901339&utm_source=setn.com&utm_medium=viewall&utm_campaign=viewallnews"}]},{"tag":"時尚","count":2,"articles":[{"topic":"春季彩妝控必收！超狂絕美「眼影盤」","dates":"02/24 21:37","url":"https://star.setn.com/news/901810?utm_source=setn.com&utm_medium=viewall&utm_campaign=viewallnews"},{"topic":"孫芸芸根本腿精！腳超開險曬神秘地帶","dates":"02/24 19:30","url":"https://star.setn.com/news/901743?utm_source=setn.com&utm_medium=viewall&utm_campaign=viewallnews"}]},{"tag":"日韓","count":7,"articles":[{"topic":"女團成員收「死亡威脅」含淚陷恐懼！","dates":"02/24 21:28","url":"https://star.setn.com/news/901822?utm_source=setn.com&utm_medium=viewall&utm_campaign=viewallnews"},{"topic":"20歲學霸AV遭起底！片酬這數字曝","dates":"02/24 20:29","url":"https://star.setn.com/news/901730?utm_source=setn.com&utm_medium=viewall&utm_campaign=viewallnews"},{"topic":"GD友爆「他們沒在藏」曝不認愛原因","dates":"02/24 19:57","url":"https://star.setn.com/news/901794?utm_source=setn.com&utm_medium=viewall&utm_campaign=viewallnews"},{"topic":"決心離開演藝圈！女星為子女搬離隱居","dates":"02/24 17:21","url":"https://star.setn.com/news/901689?utm_source=setn.com&utm_medium=viewall&utm_campaign=viewallnews"},{"topic":"韓星確診第一人　金請夏癒後憂鬱自責","dates":"02/24 14:56","url":"https://star.setn.com/news/901576?utm_source=setn.com&utm_medium=viewall&utm_campaign=viewallnews"},{"topic":"GD爆熱戀師妹1年　公司回應網笑了","dates":"02/24 11:54","url":"https://star.setn.com/news/901414?utm_source=setn.com&utm_medium=viewall&utm_campaign=viewallnews"},{"topic":"GD緋聞女友是誰？美貌像人間香奈兒","dates":"02/24 11:45","url":"https://star.setn.com/news/901449?utm_source=setn.com&utm_medium=viewall&utm_campaign=viewallnews"}]},{"tag":"電影","count":2,"articles":[{"topic":"楊祐寧曝夫妻情趣　首映會遭角頭踩場","dates":"02/24 21:16","url":"https://star.setn.com/news/901820?utm_source=setn.com&utm_medium=viewall&utm_campaign=viewallnews"},{"topic":"海底32米遇亂流　男星驚曝險回不來","dates":"02/24 15:39","url":"https://star.setn.com/news/901566?utm_source=setn.com&utm_medium=viewall&utm_campaign=viewallnews"}]},{"tag":"運動","count":38,"articles":[{"topic":"神龍再現！味全天母季票開賣就秒殺","dates":"02/24 21:01","url":"https://www.setn.com/News.aspx?NewsID=901819&utm_source=setn.com&utm_medium=viewall&utm_campaign=viewallnews"},{"topic":"現場看重播解禁　中職：聽到球迷心聲","dates":"02/24 18:42","url":"https://www.setn.com/News.aspx?NewsID=901755&utm_source=setn.com&utm_medium=viewall&utm_campaign=viewallnews"},{"topic":"羅力3局無失分　林承飛2分砲助猿勝","dates":"02/24 18:13","url":"https://www.setn.com/News.aspx?NewsID=901735&utm_source=setn.com&utm_medium=viewall&utm_campaign=viewallnews"},{"topic":"隔352天！　尼克主場開放球迷觀賽","dates":"02/24 18:05","url":"https://www.setn.com/News.aspx?NewsID=901731&utm_source=setn.com&utm_medium=viewall&utm_campaign=viewallnews"},{"topic":"梁家榮職棒7年生存競爭　頂真每一天","dates":"02/24 18:00","url":"https://www.setn.com/News.aspx?NewsID=901729&utm_source=setn.com&utm_medium=viewall&utm_campaign=viewallnews"},{"topic":"手術成功　伍茲醒了！推特發文曝傷勢","dates":"02/24 17:55","url":"https://www.setn.com/News.aspx?NewsID=901720&utm_source=setn.com&utm_medium=viewall&utm_campaign=viewallnews"},{"topic":"相隔9個月再實戰　令和怪物說出感想","dates":"02/24 17:28","url":"https://www.setn.com/News.aspx?NewsID=901700&utm_source=setn.com&utm_medium=viewall&utm_campaign=viewallnews"},{"topic":"潘威倫搶先發　中職新球縫線有安全感","dates":"02/24 17:23","url":"https://www.setn.com/News.aspx?NewsID=901703&utm_source=setn.com&utm_medium=viewall&utm_campaign=viewallnews"},{"topic":"「美胸黃捷」林襄　胸下神秘刺青曝光","dates":"02/24 17:15","url":"https://www.setn.com/News.aspx?NewsID=901663&utm_source=setn.com&utm_medium=viewall&utm_campaign=viewallnews"},{"topic":"羅暐捷連兩天全壘打　「再見轟」桃猿","dates":"02/24 16:45","url":"https://www.setn.com/News.aspx?NewsID=901657&utm_source=setn.com&utm_medium=viewall&utm_campaign=viewallnews"},{"topic":"去年因故未來台　李茲加入墨西哥聯盟","dates":"02/24 16:43","url":"https://www.setn.com/News.aspx?NewsID=901670&utm_source=setn.com&utm_medium=viewall&utm_campaign=viewallnews"},{"topic":"皮繃緊一點　阿部慎之助這句告誡選手","dates":"02/24 16:41","url":"https://www.setn.com/News.aspx?NewsID=901674&utm_source=setn.com&utm_medium=viewall&utm_campaign=viewallnews"},{"topic":"4年內2度奪冠　中油冠名開南棒球隊","dates":"02/24 15:56","url":"https://www.setn.com/News.aspx?NewsID=901620&utm_source=setn.com&utm_medium=viewall&utm_campaign=viewallnews"},{"topic":"「彈力球年代」霸主　桃猿強化投守","dates":"02/24 15:46","url":"https://www.setn.com/News.aspx?NewsID=901617&utm_source=setn.com&utm_medium=viewall&utm_campaign=viewallnews"},{"topic":"HBL總決賽　2／27開放免費索票","dates":"02/24 15:40","url":"https://www.setn.com/News.aspx?NewsID=901603&utm_source=setn.com&utm_medium=viewall&utm_campaign=viewallnews"},{"topic":"未來入主大巨蛋？中信兄弟球團回應了","dates":"02/24 15:21","url":"https://www.setn.com/News.aspx?NewsID=901596&utm_source=setn.com&utm_medium=viewall&utm_campaign=viewallnews"},{"topic":"田中粉絲俱樂部　年費破百萬限10人","dates":"02/24 15:17","url":"https://www.setn.com/News.aspx?NewsID=901599&utm_source=setn.com&utm_medium=viewall&utm_campaign=viewallnews"},{"topic":"中職不讓富邦註冊納飛猛　韓媒：屈辱","dates":"02/24 14:34","url":"https://www.setn.com/News.aspx?NewsID=901563&utm_source=setn.com&utm_medium=viewall&utm_campaign=viewallnews"},{"topic":"可愛喬治轟62分　快艇止巫師5連勝","dates":"02/24 14:16","url":"https://www.setn.com/News.aspx?NewsID=901520&utm_source=setn.com&utm_medium=viewall&utm_campaign=viewallnews"},{"topic":"梁玹種隔離4天報到春訓　41投競爭","dates":"02/24 13:43","url":"https://www.setn.com/News.aspx?NewsID=901522&utm_source=setn.com&utm_medium=viewall&utm_campaign=viewallnews"},{"topic":"久等了！獅象開幕戰門票　26日開賣","dates":"02/24 13:35","url":"https://www.setn.com/News.aspx?NewsID=901514&utm_source=setn.com&utm_medium=viewall&utm_campaign=viewallnews"},{"topic":"易肇事路段出車禍　伍茲存活非常幸運","dates":"02/24 13:30","url":"https://www.setn.com/News.aspx?NewsID=901512&utm_source=setn.com&utm_medium=viewall&utm_campaign=viewallnews"},{"topic":"牛棚投151球　齋藤球速不到130","dates":"02/24 13:21","url":"https://www.setn.com/News.aspx?NewsID=901510&utm_source=setn.com&utm_medium=viewall&utm_campaign=viewallnews"},{"topic":"阪神王牌傳不適　陳偉殷扛首戰先發？","dates":"02/24 12:57","url":"https://www.setn.com/News.aspx?NewsID=901503&utm_source=setn.com&utm_medium=viewall&utm_campaign=viewallnews"},{"topic":"恩比德只進3球　76人保住東區龍頭","dates":"02/24 12:19","url":"https://www.setn.com/News.aspx?NewsID=901468&utm_source=setn.com&utm_medium=viewall&utm_campaign=viewallnews"},{"topic":"東契奇太神！砍超遠後撤步三分準絕殺","dates":"02/24 12:13","url":"https://www.setn.com/News.aspx?NewsID=901477&utm_source=setn.com&utm_medium=viewall&utm_campaign=viewallnews"},{"topic":"復出手感依舊燙！柯瑞狂飆37分止敗","dates":"02/24 11:42","url":"https://www.setn.com/News.aspx?NewsID=901467&utm_source=setn.com&utm_medium=viewall&utm_campaign=viewallnews"},{"topic":"伍茲上次車禍　婚外情曝光又爆性成癮","dates":"02/24 11:32","url":"https://www.setn.com/News.aspx?NewsID=901463&utm_source=setn.com&utm_medium=viewall&utm_campaign=viewallnews"},{"topic":"哈登大三元　籃網首節42分！7連勝","dates":"02/24 11:23","url":"https://www.setn.com/News.aspx?NewsID=901440&utm_source=setn.com&utm_medium=viewall&utm_campaign=viewallnews"},{"topic":"一朗回水手　曝家中新成員是「姐弟」","dates":"02/24 11:09","url":"https://www.setn.com/News.aspx?NewsID=901447&utm_source=setn.com&utm_medium=viewall&utm_campaign=viewallnews"},{"topic":"明星賽替補名單出爐！怪物狀元首入選","dates":"02/24 11:04","url":"https://www.setn.com/News.aspx?NewsID=901438&utm_source=setn.com&utm_medium=viewall&utm_campaign=viewallnews"},{"topic":"剩4.7秒起飛　騎士新秀絕殺灌籃","dates":"02/24 10:53","url":"https://www.setn.com/News.aspx?NewsID=901417&utm_source=setn.com&utm_medium=viewall&utm_campaign=viewallnews"},{"topic":"連3場因傷缺陣　林書豪發文透露心聲","dates":"02/24 10:28","url":"https://www.setn.com/News.aspx?NewsID=901416&utm_source=setn.com&utm_medium=viewall&utm_campaign=viewallnews"},{"topic":"辜仲諒入主大巨蛋　成中信兄弟新家？","dates":"02/24 10:19","url":"https://www.setn.com/News.aspx?NewsID=901407&utm_source=setn.com&utm_medium=viewall&utm_campaign=viewallnews"},{"topic":"塞爾維亞驚魂24小時　曾俊欣已返台","dates":"02/24 10:04","url":"https://www.setn.com/News.aspx?NewsID=901392&utm_source=setn.com&utm_medium=viewall&utm_campaign=viewallnews"},{"topic":"樂天女孩發遲到分紅　貢獻最多是她！","dates":"02/24 09:36","url":"https://www.setn.com/News.aspx?NewsID=901364&utm_source=setn.com&utm_medium=viewall&utm_campaign=viewallnews"},{"topic":"影片曝光！老虎伍茲車禍腿複雜性骨折","dates":"02/24 09:04","url":"https://www.setn.com/News.aspx?NewsID=901328&utm_source=setn.com&utm_medium=viewall&utm_campaign=viewallnews"},{"topic":"老虎伍茲驚傳嚴重車禍　腿重傷急救中","dates":"02/24 09:03","url":"https://www.setn.com/News.aspx?NewsID=901320&utm_source=setn.com&utm_medium=viewall&utm_campaign=viewallnews"}]},{"tag":"房產","count":3,"articles":[{"topic":"千億總裁賣麵包　餐飲成未來建案標配","dates":"02/24 20:45","url":"https://www.setn.com/News.aspx?NewsID=901805&utm_source=setn.com&utm_medium=viewall&utm_campaign=viewallnews"},{"topic":"台中港搶進最後1字頭房價先卡位","dates":"02/24 14:00","url":"https://www.setn.com/News.aspx?NewsID=901519&utm_source=setn.com&utm_medium=viewall&utm_campaign=viewallnews"},{"topic":"申請自行劃定更新單元程序皆依法辦理","dates":"02/24 05:00","url":"https://www.setn.com/News.aspx?NewsID=901066&utm_source=setn.com&utm_medium=viewall&utm_campaign=viewallnews"}]},{"tag":"旅遊","count":5,"articles":[{"topic":"人在台灣也能爬到「萬里長城」！","dates":"02/24 20:00","url":"https://travel.setn.com/news/901002?utm_source=setn.com&utm_medium=viewall&utm_campaign=viewallnews"},{"topic":"限時6天！全台小七咖啡買6送6快買","dates":"02/24 18:05","url":"https://travel.setn.com/news/901725?utm_source=setn.com&utm_medium=viewall&utm_campaign=viewallnews"},{"topic":"2021南投燈會邀約國人走春遊賞","dates":"02/24 18:00","url":"https://travel.setn.com/news/901475?utm_source=setn.com&utm_medium=viewall&utm_campaign=viewallnews"},{"topic":"台式魚子醬　義大利人吃完說太銷魂！","dates":"02/24 12:00","url":"https://travel.setn.com/news/900617?utm_source=setn.com&utm_medium=viewall&utm_campaign=viewallnews"},{"topic":"超商限定櫻花季　集點抱回超粉嫩維尼","dates":"02/24 10:41","url":"https://travel.setn.com/news/901425?utm_source=setn.com&utm_medium=viewall&utm_campaign=viewallnews"}]},{"tag":"健康","count":8,"articles":[{"topic":"為何泰奶都那麼橘？營養師曝神秘原因","dates":"02/24 19:01","url":"https://www.setn.com/News.aspx?NewsID=901761&utm_source=setn.com&utm_medium=viewall&utm_campaign=viewallnews"},{"topic":"人妻上網問這問題  網友通通都歪樓","dates":"02/24 18:57","url":"https://www.setn.com/News.aspx?NewsID=901661&utm_source=setn.com&utm_medium=viewall&utm_campaign=viewallnews"},{"topic":"國內3確診躺加護病房　1人裝葉克膜","dates":"02/24 14:57","url":"https://www.setn.com/News.aspx?NewsID=901587&utm_source=setn.com&utm_medium=viewall&utm_campaign=viewallnews"},{"topic":"恐怖！醫生連得四癌　竟因小時候這樣","dates":"02/24 14:45","url":"https://www.setn.com/News.aspx?NewsID=901410&utm_source=setn.com&utm_medium=viewall&utm_campaign=viewallnews"},{"topic":"超扯！連抗4癌醫曝5大地雷飲食有它","dates":"02/24 14:45","url":"https://www.setn.com/News.aspx?NewsID=901444&utm_source=setn.com&utm_medium=viewall&utm_campaign=viewallnews"},{"topic":"親媽「這動作」害寶寶耳朵飄惡臭發炎","dates":"02/24 13:16","url":"https://www.setn.com/News.aspx?NewsID=895822&utm_source=setn.com&utm_medium=viewall&utm_campaign=viewallnews"},{"topic":"4大類藥物不能磨粉　他吃下肚出事了","dates":"02/24 12:43","url":"https://www.setn.com/News.aspx?NewsID=901492&utm_source=setn.com&utm_medium=viewall&utm_campaign=viewallnews"},{"topic":"體檢前「來一發」！恐讓攝護腺值失準","dates":"02/24 12:08","url":"https://www.setn.com/News.aspx?NewsID=901478&utm_source=setn.com&utm_medium=viewall&utm_campaign=viewallnews"}]},{"tag":"政治","count":43,"articles":[{"topic":"蔣介石到底有多狠？關鍵證據一槍斃命","dates":"02/24 18:50","url":"https://www.setn.com/News.aspx?NewsID=901773&utm_source=setn.com&utm_medium=viewall&utm_campaign=viewallnews"},{"topic":"國民黨辦論壇談未來　她一招斃命打臉","dates":"02/24 18:47","url":"https://www.setn.com/News.aspx?NewsID=901764&utm_source=setn.com&utm_medium=viewall&utm_campaign=viewallnews"},{"topic":"測蘇侯2024　名嘴抽這張牌全場驚","dates":"02/24 17:59","url":"https://www.setn.com/News.aspx?NewsID=901718&utm_source=setn.com&utm_medium=viewall&utm_campaign=viewallnews"},{"topic":"國台辦再提九二共識　陸委會回嗆這句","dates":"02/24 17:47","url":"https://www.setn.com/News.aspx?NewsID=901712&utm_source=setn.com&utm_medium=viewall&utm_campaign=viewallnews"},{"topic":"唐鳳接受日媒專訪　曝過去求學理念","dates":"02/24 17:25","url":"https://www.setn.com/News.aspx?NewsID=901682&utm_source=setn.com&utm_medium=viewall&utm_campaign=viewallnews"},{"topic":"過年拜會王金平　柯文哲認了吐7字！","dates":"02/24 17:16","url":"https://www.setn.com/News.aspx?NewsID=901688&utm_source=setn.com&utm_medium=viewall&utm_campaign=viewallnews"},{"topic":"趙叫蔡宣示不會台獨　苦苓一句破盲點","dates":"02/24 17:09","url":"https://www.setn.com/News.aspx?NewsID=901652&utm_source=setn.com&utm_medium=viewall&utm_campaign=viewallnews"},{"topic":"蔡政府藉邱太三釋善意？國台辦不領情","dates":"02/24 17:06","url":"https://www.setn.com/News.aspx?NewsID=901660&utm_source=setn.com&utm_medium=viewall&utm_campaign=viewallnews"},{"topic":"藍營挺藻礁公投有內幕？林錫耀揭真相","dates":"02/24 16:44","url":"https://www.setn.com/News.aspx?NewsID=901671&utm_source=setn.com&utm_medium=viewall&utm_campaign=viewallnews"},{"topic":"轉型正義做到好！蔡英文下軍令給任務","dates":"02/24 16:28","url":"https://www.setn.com/News.aspx?NewsID=901662&utm_source=setn.com&utm_medium=viewall&utm_campaign=viewallnews"},{"topic":"改國徽被中共點名挑釁　時力直接打臉","dates":"02/24 16:25","url":"https://www.setn.com/News.aspx?NewsID=901643&utm_source=setn.com&utm_medium=viewall&utm_campaign=viewallnews"},{"topic":"江找柯反玩殘連任路？李柏毅：重傷！","dates":"02/24 16:21","url":"https://www.setn.com/News.aspx?NewsID=901654&utm_source=setn.com&utm_medium=viewall&utm_campaign=viewallnews"},{"topic":"民調／誰要中國疫苗？民調結果超驚人","dates":"02/24 16:17","url":"https://www.setn.com/News.aspx?NewsID=901645&utm_source=setn.com&utm_medium=viewall&utm_campaign=viewallnews"},{"topic":"李來希為秦始皇道歉　綠委一句話轟爆","dates":"02/24 16:16","url":"https://www.setn.com/News.aspx?NewsID=901646&utm_source=setn.com&utm_medium=viewall&utm_campaign=viewallnews"},{"topic":"大咖都來拜年　王金平酸爆：他沒來！","dates":"02/24 16:03","url":"https://www.setn.com/News.aspx?NewsID=901578&utm_source=setn.com&utm_medium=viewall&utm_campaign=viewallnews"},{"topic":"民調／過半泛藍民眾要講「武漢肺炎」","dates":"02/24 16:03","url":"https://www.setn.com/News.aspx?NewsID=901632&utm_source=setn.com&utm_medium=viewall&utm_campaign=viewallnews"},{"topic":"堅拒藍白合！李柏毅：寧可一決死戰！","dates":"02/24 15:47","url":"https://www.setn.com/News.aspx?NewsID=901616&utm_source=setn.com&utm_medium=viewall&utm_campaign=viewallnews"},{"topic":"邱太三上任提兩岸　中共又嗆這位先生","dates":"02/24 15:42","url":"https://www.setn.com/News.aspx?NewsID=901611&utm_source=setn.com&utm_medium=viewall&utm_campaign=viewallnews"},{"topic":"國台辦批疫苗「自導自演」？阿中妙回","dates":"02/24 15:34","url":"https://www.setn.com/News.aspx?NewsID=901604&utm_source=setn.com&utm_medium=viewall&utm_campaign=viewallnews"},{"topic":"蔣介石最常處死哪種人？真相出乎意料","dates":"02/24 15:29","url":"https://www.setn.com/News.aspx?NewsID=901602&utm_source=setn.com&utm_medium=viewall&utm_campaign=viewallnews"},{"topic":"2024誰出線？洪耀福鬆口等這個人","dates":"02/24 15:13","url":"https://www.setn.com/News.aspx?NewsID=901585&utm_source=setn.com&utm_medium=viewall&utm_campaign=viewallnews"},{"topic":"柯P是能合作對象？　連勝文曝這條件","dates":"02/24 14:57","url":"https://www.setn.com/News.aspx?NewsID=901544&utm_source=setn.com&utm_medium=viewall&utm_campaign=viewallnews"},{"topic":"怎麼樣才算「台獨」？國台辦不敢回答","dates":"02/24 14:52","url":"https://www.setn.com/News.aspx?NewsID=901580&utm_source=setn.com&utm_medium=viewall&utm_campaign=viewallnews"},{"topic":"接棒鄭文燦？林智堅鬆口下一步時間點","dates":"02/24 14:43","url":"https://www.setn.com/News.aspx?NewsID=901571&utm_source=setn.com&utm_medium=viewall&utm_campaign=viewallnews"},{"topic":"殺警無罪改判　葉毓蘭：別讓他白犧牲","dates":"02/24 14:31","url":"https://www.setn.com/News.aspx?NewsID=901553&utm_source=setn.com&utm_medium=viewall&utm_campaign=viewallnews"},{"topic":"7成高中服儀違規！立委轟：違背人權","dates":"02/24 14:16","url":"https://www.setn.com/News.aspx?NewsID=901537&utm_source=setn.com&utm_medium=viewall&utm_campaign=viewallnews"},{"topic":"爆不滿藍白合作　連勝文心內話曝光了","dates":"02/24 13:53","url":"https://www.setn.com/News.aspx?NewsID=901515&utm_source=setn.com&utm_medium=viewall&utm_campaign=viewallnews"},{"topic":"邀馬228致詞惹議　柯P苦笑吐這句","dates":"02/24 12:20","url":"https://www.setn.com/News.aspx?NewsID=901484&utm_source=setn.com&utm_medium=viewall&utm_campaign=viewallnews"},{"topic":"美呼籲抗中　吳敦義：法、德不以為然","dates":"02/24 12:09","url":"https://www.setn.com/News.aspx?NewsID=901480&utm_source=setn.com&utm_medium=viewall&utm_campaign=viewallnews"},{"topic":"江啟臣尋求連任黨主席　侯友宜說話了","dates":"02/24 12:04","url":"https://www.setn.com/News.aspx?NewsID=901469&utm_source=setn.com&utm_medium=viewall&utm_campaign=viewallnews"},{"topic":"再戰2024總統？郭台銘鬆口給答案","dates":"02/24 11:50","url":"https://www.setn.com/News.aspx?NewsID=901465&utm_source=setn.com&utm_medium=viewall&utm_campaign=viewallnews"},{"topic":"同台柯惹連勝文不滿！江啟臣認了這事","dates":"02/24 11:32","url":"https://www.setn.com/News.aspx?NewsID=901459&utm_source=setn.com&utm_medium=viewall&utm_campaign=viewallnews"},{"topic":"邱太三盼兩岸春暖花開　國台辦回應了","dates":"02/24 11:28","url":"https://www.setn.com/News.aspx?NewsID=901446&utm_source=setn.com&utm_medium=viewall&utm_campaign=viewallnews"},{"topic":"正式向罷免宣戰！陳柏惟一句直接嗆爆","dates":"02/24 11:12","url":"https://www.setn.com/News.aspx?NewsID=901445&utm_source=setn.com&utm_medium=viewall&utm_campaign=viewallnews"},{"topic":"江撂話2022全面開戰　柯這樣說","dates":"02/24 11:09","url":"https://www.setn.com/News.aspx?NewsID=901439&utm_source=setn.com&utm_medium=viewall&utm_campaign=viewallnews"},{"topic":"台灣不接受九二共識？馬英九開砲4字","dates":"02/24 11:00","url":"https://www.setn.com/News.aspx?NewsID=901426&utm_source=setn.com&utm_medium=viewall&utm_campaign=viewallnews"},{"topic":"蘇貞昌拚2024？政院發言人這麼說","dates":"02/24 10:49","url":"https://www.setn.com/News.aspx?NewsID=901420&utm_source=setn.com&utm_medium=viewall&utm_campaign=viewallnews"},{"topic":"被酸蹭柯聲量　江啟臣：我不需要吧！","dates":"02/24 10:45","url":"https://www.setn.com/News.aspx?NewsID=901421&utm_source=setn.com&utm_medium=viewall&utm_campaign=viewallnews"},{"topic":"馬英九挨罵　李來希：我為秦始皇道歉","dates":"02/24 10:44","url":"https://www.setn.com/News.aspx?NewsID=901428&utm_source=setn.com&utm_medium=viewall&utm_campaign=viewallnews"},{"topic":"侮辱228受難者？馬英九傻眼吐這句","dates":"02/24 10:31","url":"https://www.setn.com/News.aspx?NewsID=901399&utm_source=setn.com&utm_medium=viewall&utm_campaign=viewallnews"},{"topic":"要出手了？吳敦義宣告五月做「這事」","dates":"02/24 10:12","url":"https://www.setn.com/News.aspx?NewsID=901387&utm_source=setn.com&utm_medium=viewall&utm_campaign=viewallnews"},{"topic":"美豬公投來勢洶洶　羅秉成：希望不過","dates":"02/24 10:08","url":"https://www.setn.com/News.aspx?NewsID=901384&utm_source=setn.com&utm_medium=viewall&utm_campaign=viewallnews"},{"topic":"台灣向中國釋善意　前藍委竟稱：心領","dates":"02/24 10:07","url":"https://www.setn.com/News.aspx?NewsID=901400&utm_source=setn.com&utm_medium=viewall&utm_campaign=viewallnews"}]},{"tag":"名家","count":15,"articles":[{"topic":"保育藻礁就可以把三接丟給台北港？","dates":"02/24 18:06","url":"https://www.setn.com/News.aspx?NewsID=901721&utm_source=setn.com&utm_medium=viewall&utm_campaign=viewallnews"},{"topic":"韓國2021絕美染髮　趨勢總整理！","dates":"02/24 17:09","url":"https://www.setn.com/News.aspx?NewsID=901451&utm_source=setn.com&utm_medium=viewall&utm_campaign=viewallnews"},{"topic":"2021春夏韓國紅棕髮色推薦！","dates":"02/24 14:02","url":"https://www.setn.com/News.aspx?NewsID=900521&utm_source=setn.com&utm_medium=viewall&utm_campaign=viewallnews"},{"topic":"三接若停擺　恐面臨空污+大量失業","dates":"02/24 13:31","url":"https://www.setn.com/News.aspx?NewsID=901507&utm_source=setn.com&utm_medium=viewall&utm_campaign=viewallnews"},{"topic":"回到初衷！關於愛我們都要更勇敢些","dates":"02/24 11:54","url":"https://www.setn.com/News.aspx?NewsID=901365&utm_source=setn.com&utm_medium=viewall&utm_campaign=viewallnews"},{"topic":"把自己還給自己吧！唯有放下才能灑脫","dates":"02/24 11:44","url":"https://www.setn.com/News.aspx?NewsID=901366&utm_source=setn.com&utm_medium=viewall&utm_campaign=viewallnews"},{"topic":"女股神偏愛創新科技！從指數看投資","dates":"02/24 11:33","url":"https://www.setn.com/News.aspx?NewsID=901357&utm_source=setn.com&utm_medium=viewall&utm_campaign=viewallnews"},{"topic":"掌握新投資策略　讓投資報酬率往上蹭","dates":"02/24 11:23","url":"https://www.setn.com/News.aspx?NewsID=901358&utm_source=setn.com&utm_medium=viewall&utm_campaign=viewallnews"},{"topic":"好消息！3種對抗塑膠微粒的創新發明","dates":"02/24 11:13","url":"https://www.setn.com/News.aspx?NewsID=901390&utm_source=setn.com&utm_medium=viewall&utm_campaign=viewallnews"},{"topic":"持續上漲中！全球富豪都在瘋彼特幣","dates":"02/24 10:39","url":"https://www.setn.com/News.aspx?NewsID=901391&utm_source=setn.com&utm_medium=viewall&utm_campaign=viewallnews"},{"topic":"3處長期疼痛注意！當心是膽結石徵兆","dates":"02/24 10:26","url":"https://www.setn.com/News.aspx?NewsID=901356&utm_source=setn.com&utm_medium=viewall&utm_campaign=viewallnews"},{"topic":"枕邊人打呼太大聲？醫教6招助改善","dates":"02/24 10:12","url":"https://www.setn.com/News.aspx?NewsID=901354&utm_source=setn.com&utm_medium=viewall&utm_campaign=viewallnews"},{"topic":"不能錯過！銅鑼炮仗花瀑布超搶眼！","dates":"02/24 08:59","url":"https://www.setn.com/News.aspx?NewsID=901352&utm_source=setn.com&utm_medium=viewall&utm_campaign=viewallnews"},{"topic":"超大型櫻花園！嘉義梅山隱藏版祕境","dates":"02/24 08:43","url":"https://www.setn.com/News.aspx?NewsID=901353&utm_source=setn.com&utm_medium=viewall&utm_campaign=viewallnews"},{"topic":"愛花者嘉年華！台北杜鵑花季即將開跑","dates":"02/24 08:08","url":"https://www.setn.com/News.aspx?NewsID=901121&utm_source=setn.com&utm_medium=viewall&utm_campaign=viewallnews"}]},{"tag":"寵物","count":2,"articles":[{"topic":"海獺跳躍get花枝　躺水面狂嗑萌翻","dates":"02/24 17:56","url":"https://www.setn.com/News.aspx?NewsID=901680&utm_source=setn.com&utm_medium=viewall&utm_campaign=viewallnews"},{"topic":"爽坐掃地機器人　喵喵下秒翻車笑翻網","dates":"02/24 08:00","url":"https://www.setn.com/News.aspx?NewsID=900921&utm_source=setn.com&utm_medium=viewall&utm_campaign=viewallnews"}]},{"tag":"寶神","count":3,"articles":[{"topic":"求子招財去病好機會！元宵習俗報你知","dates":"02/24 13:00","url":"https://www.setn.com/News.aspx?NewsID=901614&utm_source=setn.com&utm_medium=viewall&utm_campaign=viewallnews"},{"topic":"生肖開運後篇　財富桃花貴人一起來！","dates":"02/24 06:00","url":"https://www.setn.com/News.aspx?NewsID=901114&utm_source=setn.com&utm_medium=viewall&utm_campaign=viewallnews"},{"topic":"神明大日子快拜！ 關聖帝君飛昇日","dates":"02/24 06:00","url":"https://www.setn.com/News.aspx?NewsID=901217&utm_source=setn.com&utm_medium=viewall&utm_campaign=viewallnews"}]},{"tag":"女孩","count":1,"articles":[{"topic":"三生肖本周鴻運當頭　告別水逆財運旺","dates":"02/24 09:53","url":"https://watch.setn.com/video/901395?utm_source=setn.com&utm_medium=viewall&utm_campaign=viewallnews"}]}]